Workbook

Sheet Balls Calculator
F2: 1 US DOLLAR = 1 PEARL BALL
C3: RAW | D3: AMOUNT
A4: Enter Pearls Amount | B4: 499 | C4: =B4 -> 499 | D4: =TRUNC(MOD(C4,50),0) -> 49 | E4: Pearls
C5: =TRUNC(DIVIDE(C4,50),1) -> 9.9 | D5: =TRUNC(MOD(C5,10),0) -> 9 | E5: Amethyst
C6: =TRUNC(DIVIDE(C5,10),1) -> 0.9 | D6: =TRUNC(MOD(C6,10),0) -> 0 | E6: Aquamarine
C7: =TRUNC(DIVIDE(C6,10),1) -> 0 | D7: =TRUNC(C7,0) -> 0 | E7: Sapphire
D10: AMOUNT
A11: Enter Amethyst Amount | B11: 1 | D11: =B11*50 -> 50 | E11: Peals | US Dollars
D15: AMOUNT
A16: Enter Aquamarine Amount | B16: 1 | D16: =B16*10*50 -> 500 | E16: Peals | US Dollars
D20: AMOUNT
A21: Enter Sapphire Amount | B21: 1 | D21: =B21*10*10*50 -> 5000 | E21: Peals | US Dollars

Sheet Salary Calculator
A1: Salary | I1: Profits (Assuming Expenses ~75% of Earnings)
A2: Salary Per Hour (Pearls)
B3: Tier I | C3: Tier II | D3: Tier III | E3: Tier IV | F3: Tier V | G3: Tier VI
A4: Apprentice | B4: 1 | C4: 2 | D4: 3 | E4: 5 | F4: 7 | G4: 10
A5: Master | B5: 1 | C5: 3 | D5: 4 | E5: 6 | F5: 8 | G5: 15
A7: Salary Per Day (12 Hours) (Pearls) | I7: Profit Per Day (12 Hours) (Pearls)
B8: Tier I | C8: Tier II | D8: Tier III | E8: Tier IV | F8: Tier V | G8: Tier VI | J8: Tier I | K8: Tier II | L8: Tier III | M8: Tier IV | N8: Tier V | O8: Tier VI
A9: Apprentice | B9: =B4*12 -> 12 | C9: =C4*12 -> 24 | D9: =D4*12 -> 36 | E9: =E4*12 -> 60 | F9: =F4*12 -> 84 | G9: =G4*12 -> 120 | I9: Apprentice | J9: =B9*0.25 -> 3 | K9: =C9*0.25 -> 6 | L9: =D9*0.25 -> 9 | M9: =E9*0.25 -> 15 | N9: =F9*0.25 -> 21 | O9: =G9*0.25 -> 30
A10: Master | B10: =B5*12 -> 12 | C10: =C5*12 -> 36 | D10: =D5*12 -> 48 | E10: =E5*12 -> 72 | F10: =F5*12 -> 96 | G10: =G5*12 -> 180 | I10: Master | J10: =B10*0.25 -> 3 | K10: =C10*0.25 -> 9 | L10: =D10*0.25 -> 12 | M10: =E10*0.25 -> 18 | N10: =F10*0.25 -> 24 | O10: =G10*0.25 -> 45
A12: Salary Per Week (~4 Days) (Pearls) | I12: Profit Per Week (~4 Days) (Pearls)
B13: Tier I | C13: Tier II | D13: Tier III | E13: Tier IV | F13: Tier V | G13: Tier VI | J13: Tier I | K13: Tier II | L13: Tier III | M13: Tier IV | N13: Tier V | O13: Tier VI
A14: Apprentice | B14: =B9*4 -> 48 | C14: =C9*4 -> 96 | D14: =D9*4 -> 144 | E14: =E9*4 -> 240 | F14: =F9*4 -> 336 | G14: =G9*4 -> 480 | I14: Apprentice | J14: =B14*0.25 -> 12 | K14: =C14*0.25 -> 24 | L14: =D14*0.25 -> 36 | M14: =E14*0.25 -> 60 | N14: =F14*0.25 -> 84 | O14: =G14*0.25 -> 120
A15: Master | B15: =B10*4 -> 48 | C15: =C10*4 -> 144 | D15: =D10*4 -> 192 | E15: =E10*4 -> 288 | F15: =F10*4 -> 384 | G15: =G10*4 -> 720 | I15: Master | J15: =B15*0.25 -> 12 | K15: =C15*0.25 -> 36 | L15: =D15*0.25 -> 48 | M15: =E15*0.25 -> 72 | N15: =F15*0.25 -> 96 | O15: =G15*0.25 -> 180
A17: Salary Per Year (73 Weeks) (Pearls) | I17: Profit Per Year (73 Weeks) (Pearls)
B18: Tier I | C18: Tier II | D18: Tier III | E18: Tier IV | F18: Tier V | G18: Tier VI | J18: Tier I | K18: Tier II | L18: Tier III | M18: Tier IV | N18: Tier V | O18: Tier VI
A19: Apprentice | B19: =B14*73 -> 3504 | C19: =C14*73 -> 7008 | D19: =D14*73 -> 10512 | E19: =E14*73 -> 17520 | F19: =F14*73 -> 24528 | G19: =G14*73 -> 35040 | I19: Apprentice | J19: =B19*0.25 -> 876 | K19: =C19*0.25 -> 1752 | L19: =D19*0.25 -> 2628 | M19: =E19*0.25 -> 4380 | N19: =F19*0.25 -> 6132 | O19: =G19*0.25 -> 8760
A20: Master | B20: =B15*73 -> 3504 | C20: =C15*73 -> 10512 | D20: =D15*73 -> 14016 | E20: =E15*73 -> 21024 | F20: =F15*73 -> 28032 | G20: =G15*73 -> 52560 | I20: Master | J20: =B20*0.25 -> 876 | K20: =C20*0.25 -> 2628 | L20: =D20*0.25 -> 3504 | M20: =E20*0.25 -> 5256 | N20: =F20*0.25 -> 7008 | O20: =G20*0.25 -> 13140
A22: Salary Per Year (73 Weeks) (Sapphire) | I22: Profit Per Year (73 Weeks) (Sapphire)
B23: Tier I | C23: Tier II | D23: Tier III | E23: Tier IV | F23: Tier V | G23: Tier VI | J23: Tier I | K23: Tier II | L23: Tier III | M23: Tier IV | N23: Tier V | O23: Tier VI
A24: Apprentice | B24: =(B19*73)/50/10/10 -> 51.1584 | C24: =(C19*73)/50/10/10 -> 102.3168 | D24: =(D19*73)/50/10/10 -> 153.4752 | E24: =(E19*73)/50/10/10 -> 255.792 | F24: =(F19*73)/50/10/10 -> 358.1088 | G24: =(G19*73)/50/10/10 -> 511.584 | I24: Apprentice | J24: =B24*0.25 -> 12.7896 | K24: =C24*0.25 -> 25.5792 | L24: =D24*0.25 -> 38.3688 | M24: =E24*0.25 -> 63.948 | N24: =F24*0.25 -> 89.5272 | O24: =G24*0.25 -> 127.896
A25: Master | B25: =(B20*73)/50/10/10 -> 51.1584 | C25: =(C20*73)/50/10/10 -> 153.4752 | D25: =(D20*73)/50/10/10 -> 204.6336 | E25: =(E20*73)/50/10/10 -> 306.9504 | F25: =(F20*73)/50/10/10 -> 409.2672 | G25: =(G20*73)/50/10/10 -> 767.376 | I25: Master | J25: =B25*0.25 -> 12.7896 | K25: =C25*0.25 -> 38.3688 | L25: =D25*0.25 -> 51.1584 | M25: =E25*0.25 -> 76.7376 | N25: =F25*0.25 -> 102.3168 | O25: =G25*0.25 -> 191.844
H33: 1

Sheet Distance Cost Calculator
A1: Distance Cost Tier | E1: Referential Cost Chart
A2: Tier I - Cheap Goods | B2: 120 | C2: Km/Kg | E2: D.C.T | F2: 200km | G2: 400km | H2: 600km | I2: 800km | J2: 1000km | K2: 1500km | L2: 2000km
A3: Tier II - Common Goods | B3: =B2*0.7 -> 84 | C3: Km/Kg | E3: Tier I - Cheap Goods | F3: =(200/$B2)*$B$10 -> 250 | G3: =(400/$B2)*$B$10 -> 500 | H3: =(600/$B2)*$B$10 -> 750 | I3: =(800/$B2)*$B$10 -> 1000 | J3: =(1000/$B2)*$B$10 -> 1250 | K3: =(1500/$B2)*$B$10 -> 1875 | L3: =(2000/$B2)*$B$10 -> 2500
A4: Tier III - Expensive Goods | B4: =B3*0.7 -> 58.8 | C4: Km/Kg | E4: Tier II - Common Goods | F4: =(200/$B3)*$B$10 -> 357.14286 | G4: =(400/$B3)*$B$10 -> 714.28571 | H4: =(600/$B3)*$B$10 -> 1071.4286 | I4: =(800/$B3)*$B$10 -> 1428.5714 | J4: =(1000/$B3)*$B$10 -> 1785.7143 | K4: =(1500/$B3)*$B$10 -> 2678.5714 | L4: =(2000/$B3)*$B$10 -> 3571.4286
A5: Tier IV - Nobility Goods | B5: =B4*0.5 -> 29.4 | C5: Km/Kg | E5: Tier III - Expensive Goods | F5: =(200/$B4)*$B$10 -> 510.20408 | G5: =(400/$B4)*$B$10 -> 1020.4082 | H5: =(600/$B4)*$B$10 -> 1530.6122 | I5: =(800/$B4)*$B$10 -> 2040.8163 | J5: =(1000/$B4)*$B$10 -> 2551.0204 | K5: =(1500/$B4)*$B$10 -> 3826.5306 | L5: =(2000/$B4)*$B$10 -> 5102.0408
A6: *D.C.T Assumes full usage of Egua Cargo Pull limit. | E6: Tier IV - Nobility Goods | F6: =(200/$B5)*$B$10 -> 1020.4082 | G6: =(400/$B5)*$B$10 -> 2040.8163 | H6: =(600/$B5)*$B$10 -> 3061.2245 | I6: =(800/$B5)*$B$10 -> 4081.6327 | J6: =(1000/$B5)*$B$10 -> 5102.0408 | K6: =(1500/$B5)*$B$10 -> 7653.0612 | L6: =(2000/$B5)*$B$10 -> 10204.082
A7: Constants
A8: *Daily Egua Distance Limit (Ride) | B8: 65 | C8: km | E8: D.C.T Days | F8: 200km | G8: 400km | H8: 600km | I8: 800km | J8: 1000km | K8: 1500km | L8: 2000km
A9: *Daily Egua Distance Limit (Cargo) | B9: 30 | C9: km | E9: All Goods | F9: =200/$B$8 -> 3.0769231 | G9: =400/$B$8 -> 6.1538462 | H9: =600/$B$8 -> 9.2307692 | I9: =800/$B$8 -> 12.307692 | J9: =1000/$B$8 -> 15.384615 | K9: =1500/$B$8 -> 23.076923 | L9: =2000/$B$8 -> 30.769231
A10: Egua Cargo Pull Limit | B10: 150 | C10: kg *30kg for rider, etc
A13: Calculator
A14: ENTER KG | B14: 1 | C14: KG | E14: Freeish Region | M14: Gandew Region
A15: Enter D.C.T | B15: 120 | C15: Km/Kg | E15: Route | F15: Distance (Km) | G15: Tier I Cost (Pearls) | H15: Tier II Cost (Pearls) | I15: Tier III Cost (Pearls) | J15: Tier IV Cost (Pearls) | K15: ETA Ride (Days) | L15: ETA Cargo (Days) | M15: Route | N15: Distance (Km) | O15: Tier I Cost (Pearls) | P15: Tier II Cost (Pearls) | Q15: Tier III Cost (Pearls) | R15: Tier IV Cost (Pearls) | S15: ETA Ride (Days) | T15: ETA Cargo (Days)
A16: *Number of Eguas required | B16: =ROUNDUP(B14/B10,0) -> 1 | C16: =B16*B10 -> 150 | E16: Gandew Region | F16: 3293 | G16: =ROUNDUP(($F16/$B$2)*$B$14,0) -> 28 | H16: =ROUNDUP(($F16/$B$3)*$B$14,0) -> 40 | I16: =ROUNDUP(($F16/$B$4)*$B$14,0) -> 57 | J16: =ROUNDUP(($F16/$B$5)*$B$14,0) -> 113 | K16: =$F16/$B$8 -> 50.661538 | L16: =$F16/$B$9 -> 109.76667 | M16: Freeish Region | N16: 3293 | O16: =ROUNDUP(($N16/$B$2)*$B$14,0) -> 28 | P16: =ROUNDUP(($N16/$B$3)*$B$14,0) -> 40 | Q16: =ROUNDUP(($N16/$B$4)*$B$14,0) -> 57 | R16: =ROUNDUP(($N16/$B$5)*$B$14,0) -> 113 | S16: =$F16/$B$8 -> 50.661538 | T16: =$F16/$B$9 -> 109.76667
A17: *Costs are roudned up to the fullest egua cart | E17: Sanbi Region | F17: 2000 | G17: =ROUNDUP(($F17/$B$2)*$B$14,0) -> 17 | H17: =ROUNDUP(($F17/$B$3)*$B$14,0) -> 24 | I17: =ROUNDUP(($F17/$B$4)*$B$14,0) -> 35 | J17: =ROUNDUP(($F17/$B$5)*$B$14,0) -> 69 | K17: =$F17/$B$8 -> 30.769231 | L17: =$F17/$B$9 -> 66.666667 | M17: Sanbi Region | N17: 3000 | O17: =ROUNDUP((N17/$B$15)*$B$14,0) -> 25 | P17: =ROUNDUP(($N17/$B$3)*$B$14,0) -> 36 | Q17: =ROUNDUP(($N17/$B$4)*$B$14,0) -> 52 | R17: =ROUNDUP(($N17/$B$5)*$B$14,0) -> 103 | S17: =$F17/$B$8 -> 30.769231 | T17: =$F17/$B$9 -> 66.666667
E18: Tolerideme Region | F18: 3000 | G18: =ROUNDUP(($F18/$B$2)*$B$14,0) -> 25 | H18: =ROUNDUP(($F18/$B$3)*$B$14,0) -> 36 | I18: =ROUNDUP(($F18/$B$4)*$B$14,0) -> 52 | J18: =ROUNDUP(($F18/$B$5)*$B$14,0) -> 103 | K18: =$F18/$B$8 -> 46.153846 | L18: =$F18/$B$9 -> 100 | M18: Tolerideme Region | N18: 4000 | O18: =ROUNDUP((N18/$B$15)*$B$14,0) -> 34 | P18: =ROUNDUP(($N18/$B$3)*$B$14,0) -> 48 | Q18: =ROUNDUP(($N18/$B$4)*$B$14,0) -> 69 | R18: =ROUNDUP(($N18/$B$5)*$B$14,0) -> 137 | S18: =$F18/$B$8 -> 46.153846 | T18: =$F18/$B$9 -> 100
E19: Sanbi Region | M19: Tolerideme Region
E20: Route | F20: Distance (Km) | G20: Tier I Cost (Pearls) | H20: Tier II Cost (Pearls) | I20: Tier III Cost (Pearls) | J20: Tier IV Cost (Pearls) | K20: ETA Ride (Days) | L20: ETA Cargo (Days) | M20: Route | N20: Distance (Km) | O20: Tier I Cost (Pearls) | P20: Tier II Cost (Pearls) | Q20: Tier III Cost (Pearls) | R20: Tier IV Cost (Pearls) | S20: ETA Ride (Days) | T20: ETA Cargo (Days)
E21: Freeish Region | F21: 2000 | G21: =ROUNDUP(($F21/$B$2)*$B$14,0) -> 17 | H21: =ROUNDUP(($F21/$B$3)*$B$14,0) -> 24 | I21: =ROUNDUP(($F21/$B$4)*$B$14,0) -> 35 | J21: =ROUNDUP(($F21/$B$5)*$B$14,0) -> 69 | K21: =$F21/$B$8 -> 30.769231 | L21: =$F21/$B$9 -> 66.666667 | M21: Freeish Region | N21: 3000 | O21: =ROUNDUP(($N21/$B$2)*$B$14,0) -> 25 | P21: =ROUNDUP(($N21/$B$3)*$B$14,0) -> 36 | Q21: =ROUNDUP(($N21/$B$4)*$B$14,0) -> 52 | R21: =ROUNDUP(($N21/$B$5)*$B$14,0) -> 103 | S21: =$F21/$B$8 -> 30.769231 | T21: =$F21/$B$9 -> 66.666667
E22: Gandew Region | F22: 3000 | G22: =ROUNDUP(($F22/$B$2)*$B$14,0) -> 25 | H22: =ROUNDUP(($F22/$B$3)*$B$14,0) -> 36 | I22: =ROUNDUP(($F22/$B$4)*$B$14,0) -> 52 | J22: =ROUNDUP(($F22/$B$5)*$B$14,0) -> 103 | K22: =$F22/$B$8 -> 46.153846 | L22: =$F22/$B$9 -> 100 | M22: Gandew Region | N22: 4000 | O22: =ROUNDUP((N22/$B$15)*$B$14,0) -> 34 | P22: =ROUNDUP(($N22/$B$3)*$B$14,0) -> 48 | Q22: =ROUNDUP(($N22/$B$4)*$B$14,0) -> 69 | R22: =ROUNDUP(($N22/$B$5)*$B$14,0) -> 137 | S22: =$F22/$B$8 -> 46.153846 | T22: =$F22/$B$9 -> 100
E23: Tolerideme Region | F23: 1000 | G23: =ROUNDUP(($F23/$B$2)*$B$14,0) -> 9 | H23: =ROUNDUP(($F23/$B$3)*$B$14,0) -> 12 | I23: =ROUNDUP(($F23/$B$4)*$B$14,0) -> 18 | J23: =ROUNDUP(($F23/$B$5)*$B$14,0) -> 35 | K23: =$F23/$B$8 -> 15.384615 | L23: =$F23/$B$9 -> 33.333333 | M23: Sanbi Region | N23: 1000 | O23: =ROUNDUP((N23/$B$15)*$B$14,0) -> 9 | P23: =ROUNDUP(($N23/$B$3)*$B$14,0) -> 12 | Q23: =ROUNDUP(($N23/$B$4)*$B$14,0) -> 18 | R23: =ROUNDUP(($N23/$B$5)*$B$14,0) -> 35 | S23: =$F23/$B$8 -> 15.384615 | T23: =$F23/$B$9 -> 33.333333
E26: Route | F26: Distance (Km) | G26: Tier I Cost (Pearls) | H26: Tier II Cost (Pearls) | I26: Tier III Cost (Pearls) | J26: Tier IV Cost (Pearls) | K26: ETA Ride (Days) | L26: ETA Cargo (Days) | M26: Notes
E27: ForWay City - Flatland City | F27: 648 | G27: =ROUNDUP(($F27/$B$2)*$B$14,0) -> 6 | H27: =ROUNDUP(($F27/$B$3)*$B$14,0) -> 8 | I27: =ROUNDUP(($F27/$B$4)*$B$14,0) -> 12 | J27: =ROUNDUP(($F27/$B$5)*$B$14,0) -> 23 | K27: =$F27/$B$8 -> 9.9692308 | L27: =$F27/$B$9 -> 21.6
E28: ForWay City - Tolerideme Kingdom | F28: 2000 | G28: =ROUNDUP(($F28/$B$2)*$B$14,0) -> 17 | H28: =ROUNDUP(($F28/$B$3)*$B$14,0) -> 24 | I28: =ROUNDUP(($F28/$B$4)*$B$14,0) -> 35 | J28: =ROUNDUP(($F28/$B$5)*$B$14,0) -> 69 | K28: =$F28/$B$8 -> 30.769231 | L28: =$F28/$B$9 -> 66.666667
E29: ForWay City - Sanbi Kingdom | F29: 957 | G29: =ROUNDUP(($F29/$B$2)*$B$14,0) -> 8 | H29: =ROUNDUP(($F29/$B$3)*$B$14,0) -> 12 | I29: =ROUNDUP(($F29/$B$4)*$B$14,0) -> 17 | J29: =ROUNDUP(($F29/$B$5)*$B$14,0) -> 33 | K29: =$F29/$B$8 -> 14.723077 | L29: =$F29/$B$9 -> 31.9
E30: ForWay City - Freeish Kingdom | F30: 1035 | G30: =ROUNDUP(($F30/$B$2)*$B$14,0) -> 9 | H30: =ROUNDUP(($F30/$B$3)*$B$14,0) -> 13 | I30: =ROUNDUP(($F30/$B$4)*$B$14,0) -> 18 | J30: =ROUNDUP(($F30/$B$5)*$B$14,0) -> 36 | K30: =$F30/$B$8 -> 15.923077 | L30: =$F30/$B$9 -> 34.5 | M30: .+139 DeltaCross
E32: Route | F32: Distance (Km) | G32: Tier I Cost (Pearls) | H32: Tier II Cost (Pearls) | I32: Tier III Cost (Pearls) | J32: Tier IV Cost (Pearls) | K32: ETA Ride (Days) | L32: ETA Cargo (Days) | M32: Notes
D33: 1 | E33: Triangle - Whiteland | F33: 3035 | G33: =ROUNDUP(($F33/$B$2)*$B$14,0) -> 26 | H33: =ROUNDUP(($F33/$B$3)*$B$14,0) -> 37 | I33: =ROUNDUP(($F33/$B$4)*$B$14,0) -> 52 | J33: =ROUNDUP(($F33/$B$5)*$B$14,0) -> 104 | K33: =$F33/$B$8 -> 46.692308 | L33: =$F33/$B$9 -> 101.16667
E34: EndlessFog - Newland | F34: 6564 | G34: =ROUNDUP(($F34/$B$2)*$B$14,0) -> 55 | H34: =ROUNDUP(($F34/$B$3)*$B$14,0) -> 79 | I34: =ROUNDUP(($F34/$B$4)*$B$14,0) -> 112 | J34: =ROUNDUP(($F34/$B$5)*$B$14,0) -> 224 | K34: =$F34/$B$8 -> 100.98462 | L34: =$F34/$B$9 -> 218.8
G35: =ROUNDUP(($F35/$B$2)*$B$14,0) -> 0 | H35: =ROUNDUP(($F35/$B$3)*$B$14,0) -> 0 | I35: =ROUNDUP(($F35/$B$4)*$B$14,0) -> 0 | J35: =ROUNDUP(($F35/$B$5)*$B$14,0) -> 0 | K35: =$F35/$B$8 -> 0 | L35: =$F35/$B$9 -> 0
G36: =ROUNDUP(($F36/$B$2)*$B$14,0) -> 0 | H36: =ROUNDUP(($F36/$B$3)*$B$14,0) -> 0 | I36: =ROUNDUP(($F36/$B$4)*$B$14,0) -> 0 | J36: =ROUNDUP(($F36/$B$5)*$B$14,0) -> 0 | K36: =$F36/$B$8 -> 0 | L36: =$F36/$B$9 -> 0

Sheet BeastFauna Adventurer Calculato
A1: PRICES HERE ASSUME COMPARATIVE ADVANTAGE. SEE FAUNA/BEASTS BASE PRICE FOR FINAL PRICE
Q2: Egua Cargo Pull Limit (Kg) | R2: ='Distance Cost Calculator'!$B$10 -> 150 | T2: *Daily Egua Cargo Distance Limit (Km) | U2: ='Distance Cost Calculator'!$B$9 -> 30 | W2: Added Cost
Q3: Added Cost | R3: 0.2 | T3: Avg Days | U3: ='Distance Cost Calculator'!F9 -> 3.0769231 | W3: 4
A4: *Includes costs such as butchering time, and tool wear
N6: *Under most cases.
A7: Beast/Fauna | E7: Butchering | Q7: Adventurer RAW Earnings | T7: Adventurer Earnings with D.C.T | W7: City/Village Base Cost
E8: MEAT | G8: BONE | I8: OTHER | K8: USABLE | N8: WASTE*
A9: Animal | B9: Kg | C9: Pearls/Body* | E9: % | F9: Kg | G9: % | H9: Kg | I9: Other % | J9: Other (Kg) | K9: % | L9: Kg | M9: Cost (Pearl/Kg) | N9: Waste % | O9: Waste (Kg) | Q9: QTY TO FILL CART | R9: Total Pearls | T9: 200km | U9: Pearls/Day | W9: Cost (Pearl/Kg)
A10: Bagarisa | B10: 150 | C10: 750 | E10: 0.6 | F10: =E10*$B10 -> 90 | G10: 0.08 | H10: =G10*$B10 -> 12 | I10: 0.03 | J10: =I10*$B10 -> 4.5 | K10: =I10+G10+E10 -> 0.71 | L10: =J10+H10+F10 -> 106.5 | M10: =ROUNDUP((1/(F10+H10+J10))*($C10*K10),0) -> 5 | N10: =1-(I10+G10+E10) -> 0.29 | O10: =N10*$B10 -> 43.5 | Q10: ='Distance Cost Calculator'!$B$10/L10 -> 1.4084507 | R10: =(C10*$Q10)*($R$3+1) -> 1267.6056 | T10: =($R10-'Distance Cost Calculator'!F$3) -> 1017.6056 | U10: =T10/'Distance Cost Calculator'!$F$9 -> 330.72183 | W10: =ROUNDUP((T10/'Distance Cost Calculator'!$B$10)+$W$3,0) -> 11
A11: Barina | B11: 0.6 | C11: 2 | E11: 0.4 | F11: =E11*$B11 -> 0.24 | G11: 0.05 | H11: =G11*$B11 -> 0.03 | I11: 0.2 | J11: =I11*$B11 -> 0.12 | K11: =I11+G11+E11 -> 0.65 | L11: =J11+H11+F11 -> 0.39 | M11: =ROUNDUP((1/(F11+H11+J11))*($C11*K11),0) -> 4 | N11: =1-(I11+G11+E11) -> 0.35 | O11: =N11*$B11 -> 0.21 | Q11: ='Distance Cost Calculator'!$B$10/L11 -> 384.61538 | R11: =(C11*$Q11)*($R$3+1) -> 923.07692 | T11: =($R11-'Distance Cost Calculator'!F$3) -> 673.07692 | U11: =T11/'Distance Cost Calculator'!$F$9 -> 218.75 | W11: =ROUNDUP((T11/'Distance Cost Calculator'!$B$10)+$W$3,0) -> 9
A12: Big Winga | B12: 40 | C12: 300 | E12: 0.4 | F12: =E12*$B12 -> 16 | G12: 0.12 | H12: =G12*$B12 -> 4.8 | I12: 0.08 | J12: =I12*$B12 -> 3.2 | K12: =I12+G12+E12 -> 0.6 | L12: =J12+H12+F12 -> 24 | M12: =ROUNDUP((1/(F12+H12+J12))*($C12*K12),0) -> 8 | N12: =1-(I12+G12+E12) -> 0.4 | O12: =N12*$B12 -> 16 | Q12: ='Distance Cost Calculator'!$B$10/L12 -> 6.25 | R12: =(C12*$Q12)*($R$3+1) -> 2250 | T12: =($R12-'Distance Cost Calculator'!F$3) -> 2000 | U12: =T12/'Distance Cost Calculator'!$F$9 -> 650 | W12: =ROUNDUP((T12/'Distance Cost Calculator'!$B$10)+$W$3,0) -> 18
A13: Bruntos | B13: 70 | C13: 350 | E13: 0.55 | F13: =E13*$B13 -> 38.5 | G13: 0.17 | H13: =G13*$B13 -> 11.9 | I13: 0.07 | J13: =I13*$B13 -> 4.9 | K13: =I13+G13+E13 -> 0.79 | L13: =J13+H13+F13 -> 55.3 | M13: =ROUNDUP((1/(F13+H13+J13))*($C13*K13),0) -> 5 | N13: =1-(I13+G13+E13) -> 0.21 | O13: =N13*$B13 -> 14.7 | Q13: ='Distance Cost Calculator'!$B$10/L13 -> 2.7124774 | R13: =(C13*$Q13)*($R$3+1) -> 1139.2405 | T13: =($R13-'Distance Cost Calculator'!F$3) -> 889.24051 | U13: =T13/'Distance Cost Calculator'!$F$9 -> 289.00316 | W13: =ROUNDUP((T13/'Distance Cost Calculator'!$B$10)+$W$3,0) -> 10
A14: Crocus | B14: 45 | C14: 145 | E14: 0.55 | F14: =E14*$B14 -> 24.75 | G14: 0.05 | H14: =G14*$B14 -> 2.25 | I14: 0.2 | J14: =I14*$B14 -> 9 | K14: =I14+G14+E14 -> 0.8 | L14: =J14+H14+F14 -> 36 | M14: =ROUNDUP((1/(F14+H14+J14))*($C14*K14),0) -> 4 | N14: =1-(I14+G14+E14) -> 0.2 | O14: =N14*$B14 -> 9 | Q14: ='Distance Cost Calculator'!$B$10/L14 -> 4.1666667 | R14: =(C14*$Q14)*($R$3+1) -> 725 | T14: =($R14-'Distance Cost Calculator'!F$3) -> 475 | U14: =T14/'Distance Cost Calculator'!$F$9 -> 154.375 | W14: =ROUNDUP((T14/'Distance Cost Calculator'!$B$10)+$W$3,0) -> 8
A15: Egua | B15: 900 | C15: 4000 | E15: 0.57 | F15: =E15*$B15 -> 513 | G15: 0.2 | H15: =G15*$B15 -> 180 | I15: 0.06 | J15: =I15*$B15 -> 54 | K15: =I15+G15+E15 -> 0.83 | L15: =J15+H15+F15 -> 747 | M15: =ROUNDUP((1/(F15+H15+J15))*($C15*K15),0) -> 5 | N15: =1-(I15+G15+E15) -> 0.17 | O15: =N15*$B15 -> 153 | Q15: ='Distance Cost Calculator'!$B$10/L15 -> 0.20080321 | R15: =(C15*$Q15)*($R$3+1) -> 963.85542 | T15: =($R15-'Distance Cost Calculator'!F$3) -> 713.85542 | U15: =T15/'Distance Cost Calculator'!$F$9 -> 232.00301 | W15: =ROUNDUP((T15/'Distance Cost Calculator'!$B$10)+$W$3,0) -> 9
A16: Fanchaki | B16: 6.2 | C16: 35 | E16: 0.64 | F16: =E16*$B16 -> 3.968 | G16: 0.06 | H16: =G16*$B16 -> 0.372 | I16: 0.04 | J16: =I16*$B16 -> 0.248 | K16: =I16+G16+E16 -> 0.74 | L16: =J16+H16+F16 -> 4.588 | M16: =ROUNDUP((1/(F16+H16+J16))*($C16*K16),0) -> 6 | N16: =1-(I16+G16+E16) -> 0.26 | O16: =N16*$B16 -> 1.612 | Q16: ='Distance Cost Calculator'!$B$10/L16 -> 32.693984 | R16: =(C16*$Q16)*($R$3+1) -> 1373.1473 | T16: =($R16-'Distance Cost Calculator'!F$3) -> 1123.1473 | U16: =T16/'Distance Cost Calculator'!$F$9 -> 365.02289 | W16: =ROUNDUP((T16/'Distance Cost Calculator'!$B$10)+$W$3,0) -> 12
A17: Fatupari | B17: 30 | C17: 80 | E17: 0.35 | F17: =E17*$B17 -> 10.5 | G17: 0.15 | H17: =G17*$B17 -> 4.5 | I17: 0.25 | J17: =I17*$B17 -> 7.5 | K17: =I17+G17+E17 -> 0.75 | L17: =J17+H17+F17 -> 22.5 | M17: =ROUNDUP((1/(F17+H17+J17))*($C17*K17),0) -> 3 | N17: =1-(I17+G17+E17) -> 0.25 | O17: =N17*$B17 -> 7.5 | Q17: ='Distance Cost Calculator'!$B$10/L17 -> 6.6666667 | R17: =(C17*$Q17)*($R$3+1) -> 640 | T17: =($R17-'Distance Cost Calculator'!F$3) -> 390 | U17: =T17/'Distance Cost Calculator'!$F$9 -> 126.75 | W17: =ROUNDUP((T17/'Distance Cost Calculator'!$B$10)+$W$3,0) -> 7
A18: Fihi | B18: 13 | C18: 35 | E18: 0.55 | F18: =E18*$B18 -> 7.15 | G18: 0.07 | H18: =G18*$B18 -> 0.91 | I18: 0.04 | J18: =I18*$B18 -> 0.52 | K18: =I18+G18+E18 -> 0.66 | L18: =J18+H18+F18 -> 8.58 | M18: =ROUNDUP((1/(F18+H18+J18))*($C18*K18),0) -> 3 | N18: =1-(I18+G18+E18) -> 0.34 | O18: =N18*$B18 -> 4.42 | Q18: ='Distance Cost Calculator'!$B$10/L18 -> 17.482517 | R18: =(C18*$Q18)*($R$3+1) -> 734.26573 | T18: =($R18-'Distance Cost Calculator'!F$3) -> 484.26573 | U18: =T18/'Distance Cost Calculator'!$F$9 -> 157.38636 | W18: =ROUNDUP((T18/'Distance Cost Calculator'!$B$10)+$W$3,0) -> 8
A19: Flinga | B19: 100 | C19: 1000 | E19: 0.42 | F19: =E19*$B19 -> 42 | G19: 0.13 | H19: =G19*$B19 -> 13 | I19: 0.09 | J19: =I19*$B19 -> 9 | K19: =I19+G19+E19 -> 0.64 | L19: =J19+H19+F19 -> 64 | M19: =ROUNDUP((1/(F19+H19+J19))*($C19*K19),0) -> 10 | N19: =1-(I19+G19+E19) -> 0.36 | O19: =N19*$B19 -> 36 | Q19: ='Distance Cost Calculator'!$B$10/L19 -> 2.34375 | R19: =(C19*$Q19)*($R$3+1) -> 2812.5 | T19: =($R19-'Distance Cost Calculator'!F$3) -> 2562.5 | U19: =T19/'Distance Cost Calculator'!$F$9 -> 832.8125 | W19: =ROUNDUP((T19/'Distance Cost Calculator'!$B$10)+$W$3,0) -> 22
A20: Koalin | B20: 200 | C20: 650 | E20: 0.6 | F20: =E20*$B20 -> 120 | G20: 0.08 | H20: =G20*$B20 -> 16 | I20: 0.02 | J20: =I20*$B20 -> 4 | K20: =I20+G20+E20 -> 0.7 | L20: =J20+H20+F20 -> 140 | M20: =ROUNDUP((1/(F20+H20+J20))*($C20*K20),0) -> 4 | N20: =1-(I20+G20+E20) -> 0.3 | O20: =N20*$B20 -> 60 | Q20: ='Distance Cost Calculator'!$B$10/L20 -> 1.0714286 | R20: =(C20*$Q20)*($R$3+1) -> 835.71429 | T20: =($R20-'Distance Cost Calculator'!F$3) -> 585.71429 | U20: =T20/'Distance Cost Calculator'!$F$9 -> 190.35714 | W20: =ROUNDUP((T20/'Distance Cost Calculator'!$B$10)+$W$3,0) -> 8
A21: Legunia | B21: 5 | C21: 21 | E21: 0.4 | F21: =E21*$B21 -> 2 | G21: 0.09 | H21: =G21*$B21 -> 0.45 | I21: 0.05 | J21: =I21*$B21 -> 0.25 | K21: =I21+G21+E21 -> 0.54 | L21: =J21+H21+F21 -> 2.7 | M21: =ROUNDUP((1/(F21+H21+J21))*($C21*K21),0) -> 5 | N21: =1-(I21+G21+E21) -> 0.46 | O21: =N21*$B21 -> 2.3 | Q21: ='Distance Cost Calculator'!$B$10/L21 -> 55.555556 | R21: =(C21*$Q21)*($R$3+1) -> 1400 | T21: =($R21-'Distance Cost Calculator'!F$3) -> 1150 | U21: =T21/'Distance Cost Calculator'!$F$9 -> 373.75 | W21: =ROUNDUP((T21/'Distance Cost Calculator'!$B$10)+$W$3,0) -> 12
... A32: Winga/Pink Winga | B32: 2 | C32: 4 | E32: 0.4 | F32: =E32*$B32 -> 0.8 | G32: 0.1 | H32: =G32*$B32 -> 0.2 | I32: 0.07 | J32: =I32*$B32 -> 0.14 | K32: =I32+G32+E32 -> 0.57 | L32: =J32+H32+F32 -> 1.14 | M32: =ROUNDUP((1/(F32+H32+J32))*($C32*K32),0) -> 2 | N32: =1-(I32+G32+E32) -> 0.43 | O32: =N32*$B32 -> 0.86 | Q32: ='Distance Cost Calculator'!$B$10/L32 -> 131.57895 | R32: =(C32*$Q32)*($R$3+1) -> 631.57895 | T32: =($R32-'Distance Cost Calculator'!F$3) -> 381.57895 | U32: =T32/'Distance Cost Calculator'!$F$9 -> 124.01316 | W32: =ROUNDUP((T32/'Distance Cost Calculator'!$B$10)+$W$3,0) -> 7
A33: Wood People | B33: 2500 | C33: 3150 | D33: 1 | E33: 0 | F33: =E33*$B33 -> 0 | G33: 0 | H33: =G33*$B33 -> 0 | I33: 0.9 | J33: =I33*$B33 -> 2250 | K33: =I33+G33+E33 -> 0.9 | L33: =J33+H33+F33 -> 2250 | M33: =ROUNDUP((1/(F33+H33+J33))*($C33*K33),0) -> 2 | N33: =1-(I33+G33+E33) -> 0.1 | O33: =N33*$B33 -> 250 | Q33: ='Distance Cost Calculator'!$B$10/L33 -> 0.066666667 | R33: =(C33*$Q33)*($R$3+1) -> 252 | T33: =($R33-'Distance Cost Calculator'!F$3) -> 2 | U33: =T33/'Distance Cost Calculator'!$F$9 -> 0.65 | W33: =ROUNDUP((T33/'Distance Cost Calculator'!$B$10)+$W$3,0) -> 5
A34: Wooly | B34: 1700 | C34: 15000 | E34: 0.48 | F34: =E34*$B34 -> 816 | G34: 0.09 | H34: =G34*$B34 -> 153 | I34: 0.12 | J34: =I34*$B34 -> 204 | K34: =I34+G34+E34 -> 0.69 | L34: =J34+H34+F34 -> 1173 | M34: =ROUNDUP((1/(F34+H34+J34))*($C34*K34),0) -> 9 | N34: =1-(I34+G34+E34) -> 0.31 | O34: =N34*$B34 -> 527 | Q34: ='Distance Cost Calculator'!$B$10/L34 -> 0.12787724 | R34: =(C34*$Q34)*($R$3+1) -> 2301.7903 | T34: =($R34-'Distance Cost Calculator'!F$3) -> 2051.7903 | U34: =T34/'Distance Cost Calculator'!$F$9 -> 666.83184 | W34: =ROUNDUP((T34/'Distance Cost Calculator'!$B$10)+$W$3,0) -> 18
A35: Wozen | B35: 90 | C35: 600 | E35: 0.55 | F35: =E35*$B35 -> 49.5 | G35: 0.07 | H35: =G35*$B35 -> 6.3 | I35: 0.03 | J35: =I35*$B35 -> 2.7 | K35: =I35+G35+E35 -> 0.65 | L35: =J35+H35+F35 -> 58.5 | M35: =ROUNDUP((1/(F35+H35+J35))*($C35*K35),0) -> 7 | N35: =1-(I35+G35+E35) -> 0.35 | O35: =N35*$B35 -> 31.5 | Q35: ='Distance Cost Calculator'!$B$10/L35 -> 2.5641026 | R35: =(C35*$Q35)*($R$3+1) -> 1846.1538 | T35: =($R35-'Distance Cost Calculator'!F$3) -> 1596.1538 | U35: =T35/'Distance Cost Calculator'!$F$9 -> 518.75 | W35: =ROUNDUP((T35/'Distance Cost Calculator'!$B$10)+$W$3,0) -> 15
A36: Monica | B36: 0.01 | C36: 0.13 | E36: 0 | F36: =E36*$B36 -> 0 | G36: 0 | H36: =G36*$B36 -> 0 | I36: 0.9 | J36: =I36*$B36 -> 0.009 | K36: =I36+G36+E36 -> 0.9 | L36: =J36+H36+F36 -> 0.009 | M36: =ROUNDUP((1/(F36+H36+J36))*($C36*K36),0) -> 13 | N36: =1-(I36+G36+E36) -> 0.1 | O36: =N36*$B36 -> 0.001 | Q36: ='Distance Cost Calculator'!$B$10/L36 -> 16666.667 | R36: =(C36*$Q36)*($R$3+1) -> 2600 | T36: =($R36-'Distance Cost Calculator'!F$3) -> 2350 | U36: =T36/'Distance Cost Calculator'!$F$9 -> 763.75 | W36: =ROUNDUP((T36/'Distance Cost Calculator'!$B$10)+$W$3,0) -> 20
A37: Cinica | B37: 0.005 | C37: 0.01 | E37: 0 | F37: =E37*$B37 -> 0 | G37: 0 | H37: =G37*$B37 -> 0 | I37: 0.92 | J37: =I37*$B37 -> 0.0046 | K37: =I37+G37+E37 -> 0.92 | L37: =J37+H37+F37 -> 0.0046 | M37: =ROUNDUP((1/(F37+H37+J37))*($C37*K37),0) -> 2 | N37: =1-(I37+G37+E37) -> 0.08 | O37: =N37*$B37 -> 0.0004 | Q37: ='Distance Cost Calculator'!$B$10/L37 -> 32608.696 | R37: =(C37*$Q37)*($R$3+1) -> 391.30435 | T37: =($R37-'Distance Cost Calculator'!F$3) -> 141.30435 | U37: =T37/'Distance Cost Calculator'!$F$9 -> 45.923913 | W37: =ROUNDUP((T37/'Distance Cost Calculator'!$B$10)+$W$3,0) -> 5

Sheet Fauna Base Price Calculator
A1: Vars + Guide | G1: Herbivores | R1: Carnivores | AC1: Omnivores
A2: Region Color Guide | D2: Freeish Region (Tier II Avg) | G2: Winga/Pink Winga | R2: Sanbi | AC2: Soreno
A3: Comparative Advantage | D3: Route | E3: Cost (Pearls) | G3: ='BeastFauna Adventurer Calculato'!W32*$A$11 -> 7 | H3: Shipping | I3: Meat | J3: Jerky | K3: Other | L3: 25 Eggs (x2) | M3: Tamed | R3: 6 | S3: Shipping | T3: Meat | U3: Jerky | V3: Other | W3: Roe | AC3: ='BeastFauna Adventurer Calculato'!W27 -> 4 | AD3: Shipping | AE3: Meat | AF3: Other | AG3: Tamed
A4: From Freeish | D4: Gandew Region | E4: ='Distance Cost Calculator'!H16 -> 40 | G4: %Change | I4: 1 | J4: 3.48 | K4: 2.05 | L4: ~3cm | M4: Adult | R4: %Change | T4: 1 | U4: 3.02 | V4: 1.68 | W4: 4.39 | AC4: %Change | AE4: 1 | AF4: 2.15 | AG4: Adult
A5: From Gandew | D5: Sanbi Region | E5: ='Distance Cost Calculator'!H17 -> 24 | G5: UOM | H5: Kg | I5: Kg | J5: Kg | K5: Kg | L5: ~40g/Each | M5: *1 Amethyst | R5: UOM | S5: Kg | T5: Kg | U5: Kg | V5: Kg | W5: Kg | AC5: UOM | AD5: Kg | AE5: Kg | AF5: Kg
A6: From Sanbi | D6: Tolerideme Region | E6: ='Distance Cost Calculator'!H18 -> 36 | G6: Freeish | H6: 0 | I6: =($G$3*I$4)+$H6 -> 7 | J6: =($G$3*J$4)+$H6 -> 24.36 | K6: =($G$3*K$4)+$H6 -> 14.35 | L6: =25*A11 -> 25 | M6: 50 | R6: Freeish | S6: =$E$14 -> 24 | T6: =($R$3*T$4)+$S6 -> 30 | U6: =($R$3*U$4)+$S6 -> 42.12 | V6: =($R$3*V$4)+$S6 -> 34.08 | W6: =($R$3*W$4)+$S6 -> 50.34 | AC6: Freeish | AD6: 0 | AE6: =($AC$3*AE$4)+$AD6 -> 4 | AF6: =($AC$3*AF$4)+$AD6 -> 8.6 | AG6: 100
A7: From Tolerideme | D7: Gandew Region (Tier II Avg) | G7: Gandew | H7: =$E$4 -> 40 | I7: =($G$3*I$4)+$H7 -> 47 | J7: =($G$3*J$4)+$H7 -> 64.36 | K7: =($G$3*K$4)+$H7 -> 54.35 | L7: =L6+$E$4 -> 65 | M7: 75 | R7: Gandew | S7: =$E$15 -> 36 | T7: =($R$3*T$4)+$S7 -> 42 | U7: =($R$3*U$4)+$S7 -> 54.12 | V7: =($R$3*V$4)+$S7 -> 46.08 | W7: =($R$3*W$4)+$S7 -> 62.34 | AC7: Gandew | AD7: 0 | AE7: =($AC$3*AE$4)+$AD7 -> 4 | AF7: =($AC$3*AF$4)+$AD7 -> 8.6 | AG7: 100
A8: UOM Per 1kg | D8: Route | E8: Cost (Pearls) | G8: Tolerideme | H8: 0 | I8: =($G$3*I$4)+$H8 -> 7 | J8: =($G$3*J$4)+$H8 -> 24.36 | K8: =($G$3*K$4)+$H8 -> 14.35 | L8: =L6 -> 25 | M8: 50 | R8: Tolerideme | S8: =$E$16 -> 12 | T8: =($R$3*T$4)+$S8 -> 18 | U8: =($R$3*U$4)+$S8 -> 30.12 | V8: =($R$3*V$4)+$S8 -> 22.08 | W8: =($R$3*W$4)+$S8 -> 38.34 | AC8: Tolerideme | AD8: 0 | AE8: =($AC$3*AE$4)+$AD8 -> 4 | AF8: =($AC$3*AF$4)+$AD8 -> 8.6 | AG8: 100
A9: Manual UOM | D9: Freeish Region | E9: ='Distance Cost Calculator'!P16 -> 40 | G9: Sanbi | H9: 0 | I9: =($G$3*I$4)+$H9 -> 7 | J9: =($G$3*J$4)+$H9 -> 24.36 | K9: =($G$3*K$4)+$H9 -> 14.35 | L9: =L6 -> 25 | M9: 50 | R9: Sanbi | S9: 0 | T9: =($R$3*T$4)+$S9 -> 6 | U9: =($R$3*U$4)+$S9 -> 18.12 | V9: =($R$3*V$4)+$S9 -> 10.08 | W9: =($R$3*W$4)+$S9 -> 26.34 | AC9: Sanbi | AD9: 0 | AE9: =($AC$3*AE$4)+$AD9 -> 4 | AF9: =($AC$3*AF$4)+$AD9 -> 8.6 | AG9: 100
A10: Calculator Weight | D10: Sanbi Region | E10: ='Distance Cost Calculator'!P17 -> 36
A11: ='Distance Cost Calculator'!B14 -> 1 | B11: kg | D11: Tolerideme Region | E11: ='Distance Cost Calculator'!P18 -> 48
A12: *DO NOT CHANGE HERE* | D12: Sanbi Region (Tier II Avg) | G12: Egua | R12: Wozen | AC12: Bagarisa
D13: Route | E13: Cost (Pearls) | G13: ='BeastFauna Adventurer Calculato'!W15*$A$11 -> 9 | H13: Shipping | I13: Meat | J13: Jerky | K13: Other | L13: Tamed | M13: Tamed | R13: ='BeastFauna Adventurer Calculato'!W35 -> 15 | S13: Shipping | T13: Meat | U13: Jerky | V13: Other | W13: Tamed | AC13: ='BeastFauna Adventurer Calculato'!W10 -> 11 | AD13: Shipping | AE13: Meat | AF13: Jerky | AG13: Other | AH13: Tamed | AI13: Sausage
D14: Freeish Region | E14: ='Distance Cost Calculator'!H21 -> 24 | G14: %Change | I14: 1 | J14: 3.8 | K14: 1.9 | L14: Child | M14: Adult | R14: %Change | T14: 1 | U14: 2.5 | V14: 2.3 | W14: Baby | AC14: %Change | AE14: 1 | AF14: 3.6 | AG14: 1.9 | AH14: Child | AI14: 2.64
D15: Gandew Region | E15: ='Distance Cost Calculator'!H22 -> 36 | G15: UOM | H15: Kg | I15: Kg | J15: Kg | K15: Kg | L15: *1 Aquamarine | M15: *1 Sapphire | R15: UOM | S15: Kg | T15: Kg | U15: Kg | V15: Kg | AC15: UOM | AD15: Kg | AE15: Kg | AF15: Kg | AG15: Kg | AH15: *Aquamarine | AI15: Kg
D16: Tolerideme Region | E16: ='Distance Cost Calculator'!H23 -> 12 | G16: Freeish | H16: 0 | I16: =($G$13*I$14)+$H16 -> 9 | J16: =($G$13*J$14)+$H16 -> 34.2 | K16: =($G$13*K$14)+$H16 -> 17.1 | L16: 500 | M16: 5000 | R16: Freeish | S16: 0 | T16: =($R$13*T$14)+$S16 -> 15 | U16: =($R$13*U$14)+$S16 -> 37.5 | V16: =($R$13*V$14)+$S16 -> 34.5 | W16: 25 | AC16: Freeish | AD16: 0 | AE16: =($AC$13*AE$14)+$AD16 -> 11 | AF16: =($AC$13*AF$14)+$AD16 -> 39.6 | AG16: =($AC$13*AG$14)+$AD16 -> 20.9 | AH16: 500 | AI16: =($AC$13*AI$14)+$AD16 -> 29.04
D17: Tolerideme Region (Tier II Avg) | G17: Gandew | H17: =$E$4 -> 40 | I17: =($G$13*I$14)+$H17 -> 49 | J17: =($G$13*J$14)+$H17 -> 74.2 | K17: =($G$13*K$14)+$H17 -> 57.1 | L17: 1000 | M17: 6000 | R17: Gandew | S17: =$E$4 -> 40 | T17: =($R$13*T$14)+$S17 -> 55 | U17: =($R$13*U$14)+$S17 -> 77.5 | V17: =($R$13*V$14)+$S17 -> 74.5 | W17: 40 | AC17: Gandew | AD17: =$E$4 -> 40 | AE17: =($AC$13*AE$14)+$AD17 -> 51 | AF17: =($AC$13*AF$14)+$AD17 -> 79.6 | AG17: =($AC$13*AG$14)+$AD17 -> 60.9 | AH17: -- | AI17: =($AC$13*AI$14)+$AD17 -> 69.04
D18: Route | E18: Cost (Pearls) | G18: Tolerideme | H18: =$E$16 -> 12 | I18: =($G$13*I$14)+$H18 -> 21 | J18: =($G$13*J$14)+$H18 -> 46.2 | K18: =($G$13*K$14)+$H18 -> 29.1 | L18: 600 | M18: 5500 | R18: Tolerideme | S18: =$E$6 -> 36 | T18: =($R$13*T$14)+$S18 -> 51 | U18: =($R$13*U$14)+$S18 -> 73.5 | V18: =($R$13*V$14)+$S18 -> 70.5 | W18: 45 | AC18: Tolerideme | AD18: =$E$16 -> 12 | AE18: =($AC$13*AE$14)+$AD18 -> 23 | AF18: =($AC$13*AF$14)+$AD18 -> 51.6 | AG18: =($AC$13*AG$14)+$AD18 -> 32.9 | AH18: 600 | AI18: =($AC$13*AI$14)+$AD18 -> 41.04
D19: Freeish Region | E19: ='Distance Cost Calculator'!P21 -> 36 | G19: Sanbi | H19: 0 | I19: =($G$13*I$14)+$H19 -> 9 | J19: =($G$13*J$14)+$H19 -> 34.2 | K19: =($G$13*K$14)+$H19 -> 17.1 | L19: 500 | M19: 5000 | R19: Sanbi | S19: =$E$5 -> 24 | T19: =($R$13*T$14)+$S19 -> 39 | U19: =($R$13*U$14)+$S19 -> 61.5 | V19: =($R$13*V$14)+$S19 -> 58.5 | W19: 50 | AC19: Sanbi | AD19: 0 | AE19: =($AC$13*AE$14)+$AD19 -> 11 | AF19: =($AC$13*AF$14)+$AD19 -> 39.6 | AG19: =($AC$13*AG$14)+$AD19 -> 20.9 | AH19: 500 | AI19: =($AC$13*AI$14)+$AD19 -> 29.04
D20: Gandew Region | E20: ='Distance Cost Calculator'!P22 -> 48
D21: Sanbi Region | E21: ='Distance Cost Calculator'!P23 -> 12
G22: Wooly | R22: Crocus | AC22: Fanchaki
G23: ='BeastFauna Adventurer Calculato'!W34*$A$11 -> 18 | H23: Shipping | I23: Meat | J23: Jerky | K23: Other | L23: Tamed | M23: Milk | N23: Dried Milk | O23: Gyut Milk | P23: Dried Gyut Milk | R23: ='BeastFauna Adventurer Calculato'!W14 -> 8 | S23: Shipping | T23: Meat | U23: Jerky | V23: Other | W23: 9 Eggs | AC23: ='BeastFauna Adventurer Calculato'!W16 -> 12 | AD23: Shipping | AE23: Meat | AF23: Jerky | AG23: Other | AH23: 10 Eggs (2x) | AI23: Tamed
G24: %Change | I24: 1 | J24: 2.98 | K24: 2 | L24: Adult | M24: 0.4 | N24: 9.4 | O24: 0.75 | P24: 9.8 | R24: %Change | T24: 1 | U24: 3.02 | V24: 1.68 | W24: ~8cm | AC24: %Change | AE24: 1 | AF24: 3.4 | AG24: 1.9 | AH24: ~5cm | AI24: Adult
G25: UOM | H25: Kg | I25: Kg | J25: Kg | K25: Kg | L25: *3 S.A | 5 A.Q | M25: L | N25: Kg | O25: L | P25: Kg | R25: UOM | S25: Kg | T25: Kg | U25: Kg | V25: Kg | W25: ~110g/Each | AC25: UOM | AD25: Kg | AE25: Kg | AF25: Kg | AG25: Kg | AH25: ~70g/Each
G26: Freeish | H26: =$E$9 -> 40 | I26: =($G$23*I$24)+$H26 -> 58 | J26: =($G$23*J$24)+$H26 -> 93.64 | K26: =($G$23*K$24)+$H26 -> 76 | L26: -- | M26: =($G$23*M$24)+$H26 -> 47.2 | N26: =($G$23*N$24)+$H26 -> 209.2 | O26: =($G$23*O$24)+$H26 -> 53.5 | P26: =($G$23*P$24)+$H26 -> 216.4 | R26: Freeish | S26: =$E$14 -> 24 | T26: =($R$23*T$24)+$S26 -> 32 | U26: =($R$23*U$24)+$S26 -> 48.16 | V26: =($R$23*V$24)+$S26 -> 37.44 | W26: =W29+$E$14 -> 33 | AC26: Freeish | AD26: 0 | AE26: =($AC$23*AE$24)+$AD26 -> 12 | AF26: =($AC$23*AF$24)+$AD26 -> 40.8 | AG26: =($AC$23*AG$24)+$AD26 -> 22.8 | AH26: =10*A11 -> 10 | AI26: 35
G27: Gandew | H27: 0 | I27: =($G$23*I$24)+$H27 -> 18 | J27: =($G$23*J$24)+$H27 -> 53.64 | K27: =($G$23*K$24)+$H27 -> 36 | L27: 17500 | M27: =($G$23*M$24)+$H27 -> 7.2 | N27: =($G$23*N$24)+$H27 -> 169.2 | O27: =($G$23*O$24)+$H27 -> 13.5 | P27: =($G$23*P$24)+$H27 -> 176.4 | R27: Gandew | S27: =$E$15 -> 36 | T27: =($R$23*T$24)+$S27 -> 44 | U27: =($R$23*U$24)+$S27 -> 60.16 | V27: =($R$23*V$24)+$S27 -> 49.44 | W27: =W29+$E$15 -> 45 | AC27: Gandew | AD27: =$E$4 -> 40 | AE27: =($AC$23*AE$24)+$AD27 -> 52 | AF27: =($AC$23*AF$24)+$AD27 -> 80.8 | AG27: =($AC$23*AG$24)+$AD27 -> 62.8 | AH27: =AH26+$E$4 -> 50 | AI27: --
G28: Tolerideme | H28: =$E$11 -> 48 | I28: =($G$23*I$24)+$H28 -> 66 | J28: =($G$23*J$24)+$H28 -> 101.64 | K28: =($G$23*K$24)+$H28 -> 84 | L28: -- | M28: =($G$23*M$24)+$H28 -> 55.2 | N28: =($G$23*N$24)+$H28 -> 217.2 | O28: =($G$23*O$24)+$H28 -> 61.5 | P28: =($G$23*P$24)+$H28 -> 224.4 | R28: Tolerideme | S28: =$E$16 -> 12 | T28: =($R$23*T$24)+$S28 -> 20 | U28: =($R$23*U$24)+$S28 -> 36.16 | V28: =($R$23*V$24)+$S28 -> 25.44 | W28: =W29+$E$16 -> 21 | AC28: Tolerideme | AD28: 0 | AE28: =($AC$23*AE$24)+$AD28 -> 12 | AF28: =($AC$23*AF$24)+$AD28 -> 40.8 | AG28: =($AC$23*AG$24)+$AD28 -> 22.8 | AH28: =AH26 -> 10 | AI28: 29
G29: Sanbi | H29: =$E$10 -> 36 | I29: =($G$23*I$24)+$H29 -> 54 | J29: =($G$23*J$24)+$H29 -> 89.64 | K29: =($G$23*K$24)+$H29 -> 72 | L29: -- | M29: =($G$23*M$24)+$H29 -> 43.2 | N29: =($G$23*N$24)+$H29 -> 205.2 | O29: =($G$23*O$24)+$H29 -> 49.5 | P29: =($G$23*P$24)+$H29 -> 212.4 | R29: Sanbi | S29: 0 | T29: =($R$23*T$24)+$S29 -> 8 | U29: =($R$23*U$24)+$S29 -> 24.16 | V29: =($R$23*V$24)+$S29 -> 13.44 | W29: =9*A11 -> 9 | AC29: Sanbi | AD29: 0 | AE29: =($AC$23*AE$24)+$AD29 -> 12 | AF29: =($AC$23*AF$24)+$AD29 -> 40.8 | AG29: =($AC$23*AG$24)+$AD29 -> 22.8 | AH29: =AH26 -> 10 | AI29: 27
G32: Wooly (continued) | R32: Fihi
G33: =G23*$A$11 -> 18 | H33: Shipping | I33: Cheese | J33: Gyut Cheese | R33: ='BeastFauna Adventurer Calculato'!W18 -> 8 | S33: Shipping | T33: Meat | U33: Jerky | V33: Other | W33: Roe
G34: %Change | I34: 3.4 | J34: 4.1 | R34: %Change | T34: 1 | U34: 2.98 | V34: 2 | W34: 3.76
G35: UOM | H35: Kg | I35: Kg | J35: Kg | R35: UOM | S35: Kg | T35: Kg | U35: Kg | V35: Kg | W35: Kg
G36: Freeish | H36: =$E$9 -> 40 | I36: =($G$33*I$34)+$H36 -> 101.2 | J36: =($G$33*J$34)+$H36 -> 113.8 | R36: Freeish | S36: =$E$9 -> 40 | T36: =($R$33*T$34)+$S36 -> 48 | U36: =($R$33*U$34)+$S36 -> 63.84 | V36: =($R$33*V$34)+$S36 -> 56 | W36: =($R$33*W$34)+$S36 -> 70.08
G37: Gandew | H37: 0 | I37: =($G$33*I$34)+$H37 -> 61.2 | J37: =($G$33*J$34)+$H37 -> 73.8 | R37: Gandew | S37: 0 | T37: =($R$33*T$34)+$S37 -> 8 | U37: =($R$33*U$34)+$S37 -> 23.84 | V37: =($R$33*V$34)+$S37 -> 16 | W37: =($R$33*W$34)+$S37 -> 30.08
G38: Tolerideme | H38: =$E$11 -> 48 | I38: =($G$33*I$34)+$H38 -> 109.2 | J38: =($G$33*J$34)+$H38 -> 121.8 | R38: Tolerideme | S38: 0 | T38: =($R$33*T$34)+$S38 -> 8 | U38: =($R$33*U$34)+$S38 -> 23.84 | V38: =($R$33*V$34)+$S38 -> 16 | W38: =($R$33*W$34)+$S38 -> 30.08
G39: Sanbi | H39: =$E$10 -> 36 | I39: =($G$33*I$34)+$H39 -> 97.2 | J39: =($G$33*J$34)+$H39 -> 109.8 | R39: Sanbi | S39: =$E$21 -> 12 | T39: =($R$33*T$34)+$S39 -> 20 | U39: =($R$33*U$34)+$S39 -> 35.84 | V39: =($R$33*V$34)+$S39 -> 28 | W39: =($R$33*W$34)+$S39 -> 42.08
G42: Legunia | R42: Barina
G43: ='BeastFauna Adventurer Calculato'!W21*$A$11 -> 12 | H43: Shipping | I43: Meat | J43: Jerky | K43: Other | L43: 40 Eggs (2x) | M43: Tamed | R43: ='BeastFauna Adventurer Calculato'!W11 -> 9 | S43: Shipping | T43: Meat | U43: Other
G44: %Change | I44: 1 | J44: 3.76 | K44: 1.75 | L44: ~2cm | M44: Adult | R44: %Change | T44: 1 | U44: 1.9
G45: UOM | H45: Kg | I45: Kg | J45: Kg | K45: Kg | L45: ~25g/Each | R45: UOM | S45: Kg | T45: Kg | U45: Kg
G46: Freeish | H46: 0 | I46: =($G$43*I$44)+$H46 -> 12 | J46: =($G$43*J$44)+$H46 -> 45.12 | K46: =($G$43*K$44)+$H46 -> 21 | L46: =40*A11 -> 40 | M46: 25 | R46: Freeish | S46: 0 | T46: =($R$43*T$44)+$S46 -> 9 | U46: =($R$43*U$44)+$S46 -> 17.1
G47: Gandew | H47: =$E$4 -> 40 | I47: =($G$43*I$44)+$H47 -> 52 | J47: =($G$43*J$44)+$H47 -> 85.12 | K47: =($G$43*K$44)+$H47 -> 61 | L47: =L46+$E$4 -> 80 | M47: 40 | R47: Gandew | S47: =$E$4 -> 40 | T47: =($R$43*T$44)+$S47 -> 49 | U47: =($R$43*U$44)+$S47 -> 57.1
G48: Tolerideme | H48: =$E$6 -> 36 | I48: =($G$43*I$44)+$H48 -> 48 | J48: =($G$43*J$44)+$H48 -> 81.12 | K48: =($G$43*K$44)+$H48 -> 57 | L48: =L46+$E$6 -> 76 | M48: 43 | R48: Tolerideme | S48: =$E$16 -> 12 | T48: =($R$43*T$44)+$S48 -> 21 | U48: =($R$43*U$44)+$S48 -> 29.1
G49: Sanbi | H49: =$E$5 -> 24 | I49: =($G$43*I$44)+$H49 -> 36 | J49: =($G$43*J$44)+$H49 -> 69.12 | K49: =($G$43*K$44)+$H49 -> 45 | L49: =L46+$E$5 -> 64 | M49: 46 | R49: Sanbi | S49: 0 | T49: =($R$43*T$44)+$S49 -> 9 | U49: =($R$43*U$44)+$S49 -> 17.1
G52: Koalin | R52: Fatupari
G53: ='BeastFauna Adventurer Calculato'!W20*$A$11 -> 8 | H53: Shipping | I53: Meat | J53: Jerky | K53: Other | L53: Tamed | R53: ='BeastFauna Adventurer Calculato'!W17 -> 7 | S53: Shipping | T53: Meat | U53: Jerky | V53: Other | W53: 4 Eggs
G54: %Change | I54: 1 | J54: 4.12 | K54: 1.85 | L54: Baby | R54: %Change | T54: 1 | U54: 3.76 | V54: 1.75 | W54: ~10cm
G55: UOM | H55: Kg | I55: Kg | J55: Kg | K55: Kg | R55: UOM | S55: Kg | T55: Kg | U55: Kg | V55: Kg | W55: ~240g/Each
G56: Freeish | H56: =$E$14 -> 24 | I56: =($G$53*I$54)+$H56 -> 32 | J56: =($G$53*J$54)+$H56 -> 56.96 | K56: =($G$53*K$54)+$H56 -> 38.8 | L56: 110 | R56: Freeish | S56: 0 | T56: =($R$53*T$54)+$S56 -> 7 | U56: =($R$53*U$54)+$S56 -> 26.32 | V56: =($R$53*V$54)+$S56 -> 12.25 | W56: =15*A11 -> 15
G57: Gandew | H57: =$E$15 -> 36 | I57: =($G$53*I$54)+$H57 -> 44 | J57: =($G$53*J$54)+$H57 -> 68.96 | K57: =($G$53*K$54)+$H57 -> 50.8 | L57: 120 | R57: Gandew | S57: =$E$4 -> 40 | T57: =($R$53*T$54)+$S57 -> 47 | U57: =($R$53*U$54)+$S57 -> 66.32 | V57: =($R$53*V$54)+$S57 -> 52.25 | W57: =W56+$E$4 -> 55
G58: Tolerideme | H58: =$E$16 -> 12 | I58: =($G$53*I$54)+$H58 -> 20 | J58: =($G$53*J$54)+$H58 -> 44.96 | K58: =($G$53*K$54)+$H58 -> 26.8 | L58: 90 | R58: Tolerideme | S58: =$E$6 -> 36 | T58: =($R$53*T$54)+$S58 -> 43 | U58: =($R$53*U$54)+$S58 -> 62.32 | V58: =($R$53*V$54)+$S58 -> 48.25 | W58: =W56+$E$6 -> 51
G59: Sanbi | H59: 0 | I59: =($G$53*I$54)+$H59 -> 8 | J59: =($G$53*J$54)+$H59 -> 32.96 | K59: =($G$53*K$54)+$H59 -> 14.8 | L59: 80 | R59: Sanbi | S59: =$E$5 -> 24 | T59: =($R$53*T$54)+$S59 -> 31 | U59: =($R$53*U$54)+$S59 -> 50.32 | V59: =($R$53*V$54)+$S59 -> 36.25 | W59: =W56+$E$5 -> 39
G62: Monica | R62: Sayna
G63: ='BeastFauna Adventurer Calculato'!W36*$A$11 -> 20 | H63: Shipping | I63: Other | R63: ='BeastFauna Adventurer Calculato'!W25 -> 9 | S63: Shipping | T63: Meat | U63: Jerky | V63: Other | W63: Tamed
G64: %Change | I64: 1 | R64: %Change | T64: 1 | U64: 2.1 | V64: 2.35 | W64: Adult
G65: UOM | H65: Kg | I65: Kg | R65: UOM | S65: Kg | T65: Kg | U65: Kg | V65: Kg
G66: Freeish | H66: 0 | I66: =($G$63*I$64)+$H66 -> 20 | R66: Freeish | S66: =$E$9 -> 40 | T66: =($R$63*T$64)+$S66 -> 49 | U66: =($R$63*U$64)+$S66 -> 58.9 | V66: =($R$63*V$64)+$S66 -> 61.15 | W66: 115
G67: Gandew | H67: =$E$4 -> 40 | I67: =($G$63*I$64)+$H67 -> 60 | R67: Gandew | S67: 0 | T67: =($R$63*T$64)+$S67 -> 9 | U67: =($R$63*U$64)+$S67 -> 18.9 | V67: =($R$63*V$64)+$S67 -> 21.15 | W67: 100
G68: Tolerideme | H68: =$E$16 -> 12 | I68: =($G$63*I$64)+$H68 -> 32 | R68: Tolerideme | S68: =$E$11 -> 48 | T68: =($R$63*T$64)+$S68 -> 57 | U68: =($R$63*U$64)+$S68 -> 66.9 | V68: =($R$63*V$64)+$S68 -> 69.15 | W68: 120
G69: Sanbi | H69: 0 | I69: =($G$63*I$64)+$H69 -> 20 | R69: Sanbi | S69: =$E$10 -> 36 | T69: =($R$63*T$64)+$S69 -> 45 | U69: =($R$63*U$64)+$S69 -> 54.9 | V69: =($R$63*V$64)+$S69 -> 57.15 | W69: 125
G72: Cinika
G73: ='BeastFauna Adventurer Calculato'!W37*$A$11 -> 5 | H73: Shipping | I73: Other
G74: %Change | I74: 1
G75: UOM | H75: Kg | I75: Kg
G76: Freeish | H76: 0 | I76: =($G$73*I$74)+$H76 -> 5
G77: Gandew | H77: =$E$4 -> 40 | I77: =($G$73*I$74)+$H77 -> 45
G78: Tolerideme | H78: =$E$16 -> 12 | I78: =($G$73*I$74)+$H78 -> 17
G79: Sanbi | H79: 0 | I79: =($G$73*I$74)+$H79 -> 5

Sheet Beast Base Price Calculator
A1: Vars + Guide | G1: Aggresive | R1: Defensive | AC1: Amicable
A2: Region Color Guide | D2: Freeish Region (Tier II Avg) | G2: Sand Worm | R2: Sweet Sting | AC2: Flinga
A3: Comparative Advantage | D3: Route | E3: Cost (Pearls) | G3: ='BeastFauna Adventurer Calculato'!W24 -> 5 | H3: Shipping | I3: Meat | J3: Jerky | K3: Other | L3: 7 Eggs | R3: ='BeastFauna Adventurer Calculato'!W28 -> 8 | S3: Shipping | T3: Other | U3: Black Honey | V3: Black Mead | AC3: ='BeastFauna Adventurer Calculato'!W19 -> 22 | AD3: Shipping | AE3: Meat | AF3: Jerky | AG3: Other | AH3: 1 Egg | AI3: Tamed
A4: From Freeish | D4: Gandew Region | E4: ='Distance Cost Calculator'!H16 -> 40 | G4: %Change | I4: 1 | J4: 2.3 | K4: 2.71 | L4: ~3cm | R4: %Change | T4: 1 | U4: 2.94 | V4: 3.15 | AC4: %Change | AE4: 1 | AF4: 2.45 | AG4: 4.25 | AH4: ~65cm | AI4: Adult
A5: From Gandew | D5: Sanbi Region | E5: ='Distance Cost Calculator'!H17 -> 24 | G5: UOM | H5: Kg | I5: Kg | J5: Kg | K5: Kg | L5: ~140g/Each | R5: UOM | S5: Kg | T5: Kg | U5: L | V5: L | AC5: UOM | AD5: Kg | AE5: Kg | AF5: Kg | AG5: Kg | AH5: ~1.4Kg/Each | 1 S.A | AI5: *10 S.A
A6: From Sanbi | D6: Tolerideme Region | E6: ='Distance Cost Calculator'!H18 -> 36 | G6: Freeish | H6: =$E$9 -> 40 | I6: =($G$3*I$4)+$H6 -> 45 | J6: =($G$3*J$4)+$H6 -> 51.5 | K6: =($G$3*K$4)+$H6 -> 53.55 | L6: =L7+H6 -> 47 | R6: Freeish | S6: 0 | T6: =($R$3*T$4)+$S6 -> 8 | U6: =($R$3*U$4)+$S6 -> 23.52 | V6: =($R$3*V$4)+$S6 -> 25.2 | AC6: Freeish | AD6: 0 | AE6: =($AC$3*AE$4)+$AD6 -> 22 | AF6: =($AC$3*AF$4)+$AD6 -> 53.9 | AG6: =($AC$3*AG$4)+$AD6 -> 93.5 | AH6: 5000 | AI6: 50000
A7: From Tolerideme | D7: Gandew Region (Tier II Avg) | G7: Gandew | H7: 0 | I7: =($G$3*I$4)+$H7 -> 5 | J7: =($G$3*J$4)+$H7 -> 11.5 | K7: =($G$3*K$4)+$H7 -> 13.55 | L7: =7*A11 -> 7 | R7: Gandew | S7: =$E$4 -> 40 | T7: =($R$3*T$4)+$S7 -> 48 | U7: =($R$3*U$4)+$S7 -> 63.52 | V7: =($R$3*V$4)+$S7 -> 65.2 | AC7: Gandew | AD7: 0 | AE7: =($AC$3*AE$4)+$AD7 -> 22 | AF7: =($AC$3*AF$4)+$AD7 -> 53.9 | AG7: =($AC$3*AG$4)+$AD7 -> 93.5 | AH7: 5000 | AI7: 50000
A8: UOM Per 1kg | D8: Route | E8: Cost (Pearls) | G8: Tolerideme | H8: =$E$11 -> 48 | I8: =($G$3*I$4)+$H8 -> 53 | J8: =($G$3*J$4)+$H8 -> 59.5 | K8: =($G$3*K$4)+$H8 -> 61.55 | L8: =L7+H8 -> 55 | R8: Tolerideme | S8: =$E$6 -> 36 | T8: =($R$3*T$4)+$S8 -> 44 | U8: =($R$3*U$4)+$S8 -> 59.52 | V8: =($R$3*V$4)+$S8 -> 61.2 | AC8: Tolerideme | AD8: 0 | AE8: =($AC$3*AE$4)+$AD8 -> 22 | AF8: =($AC$3*AF$4)+$AD8 -> 53.9 | AG8: =($AC$3*AG$4)+$AD8 -> 93.5 | AH8: 5000 | AI8: 50000
A9: Manual UOM | D9: Freeish Region | E9: ='Distance Cost Calculator'!P16 -> 40 | G9: Sanbi | H9: =$E$10 -> 36 | I9: =($G$3*I$4)+$H9 -> 41 | J9: =($G$3*J$4)+$H9 -> 47.5 | K9: =($G$3*K$4)+$H9 -> 49.55 | L9: =L7+H9 -> 43 | R9: Sanbi | S9: =$E$5 -> 24 | T9: =($R$3*T$4)+$S9 -> 32 | U9: =($R$3*U$4)+$S9 -> 47.52 | V9: =($R$3*V$4)+$S9 -> 49.2 | AC9: Sanbi | AD9: 0 | AE9: =($AC$3*AE$4)+$AD9 -> 22 | AF9: =($AC$3*AF$4)+$AD9 -> 53.9 | AG9: =($AC$3*AG$4)+$AD9 -> 93.5 | AH9: 5000 | AI9: 50000
A10: Calculator Weight | D10: Sanbi Region | E10: ='Distance Cost Calculator'!P17 -> 36
A11: ='Distance Cost Calculator'!B14 -> 1 | B11: kg | D11: Tolerideme Region | E11: ='Distance Cost Calculator'!P18 -> 48
A12: *DO NOT CHANGE HERE* | D12: Sanbi Region (Tier II Avg) | G12: Walking Flathead | R12: Big Winga | AC12: Nari Worms
D13: Route | E13: Cost (Pearls) | G13: ='BeastFauna Adventurer Calculato'!W30 -> 21 | H13: Shipping | I13: Other | R13: ='BeastFauna Adventurer Calculato'!W12 -> 18 | S13: Shipping | T13: Meat | U13: Jerky | V13: Other | W13: 1 Egg | X13: Tamed | AC13: ='BeastFauna Adventurer Calculato'!W22 -> 11 | AD13: Shipping | AE13: Meat | AF13: Jerky | AG13: Other | AH13: 5 Eggs | AI13: Nari Stone
D14: Freeish Region | E14: ='Distance Cost Calculator'!H21 -> 24 | G14: %Change | I14: 1 | R14: %Change | T14: 1 | U14: 4.25 | V14: 2.05 | W14: ~35cm | X14: Adult | AC14: %Change | AE14: 1 | AF14: 3.42 | AG14: 2 | AH14: ~5cm | AI14: ~5cm
D15: Gandew Region | E15: ='Distance Cost Calculator'!H22 -> 36 | G15: UOM | H15: Kg | I15: Kg | R15: UOM | S15: Kg | T15: Kg | U15: Kg | V15: Kg | W15: ~700g/Each | X15: *1 Aquamarine | AC15: UOM | AD15: Kg | AE15: Kg | AF15: Kg | AG15: Kg | AH15: ~200g/Each
D16: Tolerideme Region | E16: ='Distance Cost Calculator'!H23 -> 12 | G16: Freeish | H16: =$E$19 -> 36 | I16: =($G$13*I$14)+$H16 -> 57 | R16: Freeish | S16: 0 | T16: =($R$13*T$14)+$S16 -> 18 | U16: =($R$13*U$14)+$S16 -> 76.5 | V16: =($R$13*V$14)+$S16 -> 36.9 | W16: =10*A11 -> 10 | X16: 500 | AC16: Freeish | AD16: 0 | AE16: =($AC$13*AE$14)+$AD16 -> 11 | AF16: =($AC$13*AF$14)+$AD16 -> 37.62 | AG16: =($AC$13*AG$14)+$AD16 -> 22 | AH16: =375*A11 -> 375 | AI16: 50
D17: Tolerideme Region (Tier II Avg) | G17: Gandew | H17: =$E$20 -> 48 | I17: =($G$13*I$14)+$H17 -> 69 | R17: Gandew | S17: =$E$4 -> 40 | T17: =($R$13*T$14)+$S17 -> 58 | U17: =($R$13*U$14)+$S17 -> 116.5 | V17: =($R$13*V$14)+$S17 -> 76.9 | W17: =W16+$E$4 -> 50 | X17: 750 | AC17: Gandew | AD17: =$E$4 -> 40 | AE17: =($AC$13*AE$14)+$AD17 -> 51 | AF17: =($AC$13*AF$14)+$AD17 -> 77.62 | AG17: =($AC$13*AG$14)+$AD17 -> 62 | AH17: =AH16+AD17 -> 415 | AI17: 50
D18: Route | E18: Cost (Pearls) | G18: Tolerideme | H18: 0 | I18: =($G$13*I$14)+$H18 -> 21 | R18: Tolerideme | S18: 0 | T18: =($R$13*T$14)+$S18 -> 18 | U18: =($R$13*U$14)+$S18 -> 76.5 | V18: =($R$13*V$14)+$S18 -> 36.9 | W18: =W16 -> 10 | X18: 500 | AC18: Tolerideme | AD18: =$E$6 -> 36 | AE18: =($AC$13*AE$14)+$AD18 -> 47 | AF18: =($AC$13*AF$14)+$AD18 -> 73.62 | AG18: =($AC$13*AG$14)+$AD18 -> 58 | AH18: =AH16+AD18 -> 411 | AI18: 50
D19: Freeish Region | E19: ='Distance Cost Calculator'!P21 -> 36 | G19: Sanbi | H19: =$E$21 -> 12 | I19: =($G$13*I$14)+$H19 -> 33 | R19: Sanbi | S19: 0 | T19: =($R$13*T$14)+$S19 -> 18 | U19: =($R$13*U$14)+$S19 -> 76.5 | V19: =($R$13*V$14)+$S19 -> 36.9 | W19: =W16 -> 10 | X19: 500 | AC19: Sanbi | AD19: =$E$5 -> 24 | AE19: =($AC$13*AE$14)+$AD19 -> 35 | AF19: =($AC$13*AF$14)+$AD19 -> 61.62 | AG19: =($AC$13*AG$14)+$AD19 -> 46 | AH19: =AH16+AD19 -> 399 | AI19: 50
D20: Gandew Region | E20: ='Distance Cost Calculator'!P22 -> 48
D21: Sanbi Region | E21: ='Distance Cost Calculator'!P23 -> 12
G22: Wood People | R22: Trunk People | AC22: Bruntos
G23: ='BeastFauna Adventurer Calculato'!W33 -> 5 | H23: Shipping | I23: Other | R23: ='BeastFauna Adventurer Calculato'!W29 -> 5 | S23: Shipping | T23: Other | AC23: ='BeastFauna Adventurer Calculato'!W13 -> 10 | AD23: Shipping | AE23: Meat | AF23: Jerky | AG23: Other | AH23: Tamed
G24: %Change | I24: 1 | R24: %Change | T24: 1 | AC24: %Change | AE24: 1 | AF24: 3.15 | AG24: 1.5
G25: UOM | H25: Kg | I25: Kg | R25: UOM | S25: Kg | T25: Kg | AC25: UOM | AD25: Kg | AE25: Kg | AF25: Kg | AG25: Kg
G26: Freeish | H26: =$E$19 -> 36 | I26: =($G$23*I$24)+$H26 -> 41 | R26: Freeish | S26: 0 | T26: =($R$23*T$24)+$S26 -> 5 | AC26: Freeish | AD26: 0 | AE26: =($AC$23*AE$24)+$AD26 -> 10 | AF26: =($AC$23*AF$24)+$AD26 -> 31.5 | AG26: =($AC$23*AG$24)+$AD26 -> 15 | AH26: --
G27: Gandew | H27: =$E$20 -> 48 | I27: =($G$23*I$24)+$H27 -> 53 | R27: Gandew | S27: =$E$4 -> 40 | T27: =($R$23*T$24)+$S27 -> 45 | AC27: Gandew | AD27: =$E$4 -> 40 | AE27: =($AC$23*AE$24)+$AD27 -> 50 | AF27: =($AC$23*AF$24)+$AD27 -> 71.5 | AG27: =($AC$23*AG$24)+$AD27 -> 55 | AH27: --
G28: Tolerideme | H28: 0 | I28: =($G$23*I$24)+$H28 -> 5 | R28: Tolerideme | S28: =$E$6 -> 36 | T28: =($R$23*T$24)+$S28 -> 41 | AC28: Tolerideme | AD28: =$E$6 -> 36 | AE28: =($AC$23*AE$24)+$AD28 -> 46 | AF28: =($AC$23*AF$24)+$AD28 -> 67.5 | AG28: =($AC$23*AG$24)+$AD28 -> 51 | AH28: --
G29: Sanbi | H29: =$E$21 -> 12 | I29: =($G$23*I$24)+$H29 -> 17 | R29: Sanbi | S29: =$E$5 -> 24 | T29: =($R$23*T$24)+$S29 -> 29 | AC29: Sanbi | AD29: =$E$5 -> 24 | AE29: =($AC$23*AE$24)+$AD29 -> 34 | AF29: =($AC$23*AF$24)+$AD29 -> 55.5 | AG29: =($AC$23*AG$24)+$AD29 -> 39 | AH29: --
R32: Shapeshifter | AC32: White Roundies
R33: ='BeastFauna Adventurer Calculato'!W26 -> 13 | S33: Shipping | T33: Other | AC33: ='BeastFauna Adventurer Calculato'!W31 -> 7 | AD33: Shipping | AE33: Meat | AF33: Jerky | AG33: Other
R34: %Change | T34: 1 | AC34: %Change | AE34: 1 | AF34: 3.62 | AG34: 5.28
R35: UOM | S35: Kg | T35: Kg | AC35: UOM | AD35: Kg | AE35: Kg | AF35: Kg
R36: Freeish | S36: 0 | T36: =($R$33*T$34)+$S36 -> 13 | AC36: Freeish | AD36: 0 | AE36: =($AC$33*AE$34)+$AD36 -> 7 | AF36: =($AC$33*AF$34)+$AD36 -> 25.34 | AG36: =($AC$33*AG$34)+$AD36 -> 36.96
R37: Gandew | S37: =$E$4 -> 40 | T37: =($R$33*T$34)+$S37 -> 53 | AC37: Gandew | AD37: =$E$4 -> 40 | AE37: =($AC$33*AE$34)+$AD37 -> 47 | AF37: =($AC$33*AF$34)+$AD37 -> 65.34 | AG37: =($AC$33*AG$34)+$AD37 -> 76.96
R38: Tolerideme | S38: =$E$6 -> 36 | T38: =($R$33*T$34)+$S38 -> 49 | AC38: Tolerideme | AD38: =$E$16 -> 12 | AE38: =($AC$33*AE$34)+$AD38 -> 19 | AF38: =($AC$33*AF$34)+$AD38 -> 37.34 | AG38: =($AC$33*AG$34)+$AD38 -> 48.96
R39: Sanbi | S39: =$E$5 -> 24 | T39: =($R$33*T$34)+$S39 -> 37 | AC39: Sanbi | AD39: 0 | AE39: =($AC$33*AE$34)+$AD39 -> 7 | AF39: =($AC$33*AF$34)+$AD39 -> 25.34 | AG39: =($AC$33*AG$34)+$AD39 -> 36.96

Sheet Flora Base Price Calculator
A1: Vars + Guide | G1: Shrubs | N1: Plants | R1: Fruit Trees | AA1: Non-fruit Trees | AF1: Grass | AO1: Mushrooms | AS1: Roots
A2: Region Color Guide | D2: Freeish Region (Tier I Avg) | G2: Gyut | N2: Girdol | R2: Cocona | AA2: Tastyleaf | AF2: Carbey | AO2: Lakata | AS2: Cadioca
A3: Comparative Advantage | D3: Route | E3: Cost (Pearls) | G3: 1 | H3: Shipping | I3: Berries | J3: Dried | K3: Juice | L3: Hard Juice | N3: 45 | O3: Shipping | P3: Flowers | R3: 3 | S3: Shipping | T3: Single Fruit | U3: Fruit | V3: Dried | W3: Juice | X3: Hard Juice | AA3: 20 | AB3: Shipping | AC3: Fresh Leaves | AD3: Grounded Leaves | AF3: 1 | AG3: Shipping | AH3: RAW | AI3: Flour | AJ3: Bread | AK3: Beer | AL3: Ale | AO3: 125 | AP3: Shipping | AQ3: Caps | AS3: 2 | AT3: Shipping | AU3: RAW | AV3: Coarse Flour | AW3: Flour | AX3: Bread
A4: From Freeish | D4: Gandew Region | E4: ='Distance Cost Calculator'!G16 -> 28 | G4: %Change | I4: 1 | J4: 10 | K4: 1.3 | L4: 1.4 | N4: %Change | P4: 1 | R4: %Change | T4: ~78cm | U4: 1 | V4: 9.5 | W4: 1.5 | X4: 1.75 | AA4: %Change | AC4: 1 | AD4: 1.3 | AF4: %Change | AH4: 1 | AI4: 3.1 | AJ4: 3.5 | AK4: 3.4 | AL4: 4.2 | AO4: %Change | AQ4: 1 | AS4: %Change | AU4: 1 | AV4: 2.1 | AW4: 3 | AX4: 1.5
A5: From Gandew | D5: Sanbi Region | E5: ='Distance Cost Calculator'!G17 -> 17 | G5: UOM | H5: Kg | I5: Kg | J5: Kg | K5: L | L5: L | N5: UOM | O5: Kg | P5: Kg | R5: UOM | S5: Kg | T5: ~2kg - 70% Edible | U5: Kg | V5: Kg | W5: L | X5: L | AA5: UOM | AB5: Kg | AC5: Kg | AD5: Kg | AF5: UOM | AG5: Kg | AH5: Kg | AI5: Kg | AJ5: Kg | AK5: L | AL5: L | AO5: UOM | AP5: Kg | AQ5: Kg | AS5: UOM | AT5: Kg | AU5: Kg | AV5: Kg | AW5: Kg | AX5: Kg
A6: From Sanbi | D6: Tolerideme Region | E6: ='Distance Cost Calculator'!G18 -> 25 | G6: Freeish | H6: 0 | I6: =($G$3*I$4)+$H6 -> 1 | J6: =($G$3*J$4)+$H6 -> 10 | K6: =($G$3*K$4)+$H6 -> 1.3 | L6: =($G$3*L$4)+$H6 -> 1.4 | N6: Freeish | O6: =$E$14 -> 17 | P6: =($N$3*P$4)+$O6 -> 62 | R6: Freeish | S6: 0 | T6: =U6*2 -> 6 | U6: =($R$3*U$4)+$S6 -> 3 | V6: =($R$3*V$4)+$S6 -> 28.5 | W6: =($R$3*W$4)+$S6 -> 4.5 | X6: =($R$3*X$4)+$S6 -> 5.25 | AA6: Freeish | AB6: =$E$14 -> 17 | AC6: =($AA$3*AC$4)+$AB6 -> 37 | AD6: =($AA$3*AD$4)+$AB6 -> 43 | AF6: Freeish | AG6: 0 | AH6: =($AF$3*AH$4)+$AG6 -> 1 | AI6: =($AF$3*AI$4)+$AG6 -> 3.1 | AJ6: =($AF$3*AJ$4)+$AG6 -> 3.5 | AK6: =($AF$3*AK$4)+$AG6 -> 3.4 | AL6: =($AF$3*AL$4)+$AG6 -> 4.2 | AO6: Freeish | AP6: 0 | AQ6: =($AO$3*AQ$4)+$AP6 -> 125 | AS6: Freeish | AT6: 0 | AU6: =($AS$3*AU$4)+$AT6 -> 2 | AV6: =($AS$3*AV$4)+$AT6 -> 4.2 | AW6: =($AS$3*AW$4)+$AT6 -> 6 | AX6: =($AS$3*AX$4)+$AT6 -> 3
A7: From Tolerideme | D7: Gandew Region (Tier I Avg) | G7: Gandew | H7: =$E$4 -> 28 | I7: =($G$3*I$4)+$H7 -> 29 | J7: =($G$3*J$4)+$H7 -> 38 | K7: =($G$3*K$4)+$H7 -> 29.3 | L7: =($G$3*L$4)+$H7 -> 29.4 | N7: Gandew | O7: =$E$15 -> 25 | P7: =($N$3*P$4)+$O7 -> 70 | R7: Gandew | S7: =$E$4 -> 28 | T7: =U7*2 -> 62 | U7: =($R$3*U$4)+$S7 -> 31 | V7: =($R$3*V$4)+$S7 -> 56.5 | W7: =($R$3*W$4)+$S7 -> 32.5 | X7: =($R$3*X$4)+$S7 -> 33.25 | AA7: Gandew | AB7: =$E$15 -> 25 | AC7: =($AA$3*AC$4)+$AB7 -> 45 | AD7: =($AA$3*AD$4)+$AB7 -> 51 | AF7: Gandew | AG7: =$E$4 -> 28 | AH7: =($AF$3*AH$4)+$AG7 -> 29 | AI7: =($AF$3*AI$4)+$AG7 -> 31.1 | AJ7: =($AF$3*AJ$4)+$AG7 -> 31.5 | AK7: =($AF$3*AK$4)+$AG7 -> 31.4 | AL7: =($AF$3*AL$4)+$AG7 -> 32.2 | AO7: Gandew | AP7: =$E$4 -> 28 | AQ7: =($AO$3*AQ$4)+$AP7 -> 153 | AS7: Gandew | AT7: =$E$4 -> 28 | AU7: =($AS$3*AU$4)+$AT7 -> 30 | AV7: =($AS$3*AV$4)+$AT7 -> 32.2 | AW7: =($AS$3*AW$4)+$AT7 -> 34 | AX7: =($AS$3*AX$4)+$AT7 -> 31
A8: UOM Per 1kg | D8: Route | E8: Cost (Pearls) | G8: Tolerideme | H8: =$E$16 -> 9 | I8: =($G$3*I$4)+$H8 -> 10 | J8: =($G$3*J$4)+$H8 -> 19 | K8: =($G$3*K$4)+$H8 -> 10.3 | L8: =($G$3*L$4)+$H8 -> 10.4 | N8: Tolerideme | O8: =$E$16 -> 9 | P8: =($N$3*P$4)+$O8 -> 54 | R8: Tolerideme | S8: =$E$16 -> 9 | T8: =U8*2 -> 24 | U8: =($R$3*U$4)+$S8 -> 12 | V8: =($R$3*V$4)+$S8 -> 37.5 | W8: =($R$3*W$4)+$S8 -> 13.5 | X8: =($R$3*X$4)+$S8 -> 14.25 | AA8: Tolerideme | AB8: =$E$16 -> 9 | AC8: =($AA$3*AC$4)+$AB8 -> 29 | AD8: =($AA$3*AD$4)+$AB8 -> 35 | AF8: Tolerideme | AG8: =$E$16 -> 9 | AH8: =($AF$3*AH$4)+$AG8 -> 10 | AI8: =($AF$3*AI$4)+$AG8 -> 12.1 | AJ8: =($AF$3*AJ$4)+$AG8 -> 12.5 | AK8: =($AF$3*AK$4)+$AG8 -> 12.4 | AL8: =($AF$3*AL$4)+$AG8 -> 13.2 | AO8: Tolerideme | AP8: =$E$6 -> 25 | AQ8: =($AO$3*AQ$4)+$AP8 -> 150 | AS8: Tolerideme | AT8: =$E$6 -> 25 | AU8: =($AS$3*AU$4)+$AT8 -> 27 | AV8: =($AS$3*AV$4)+$AT8 -> 29.2 | AW8: =($AS$3*AW$4)+$AT8 -> 31 | AX8: =($AS$3*AX$4)+$AT8 -> 28
A9: Manual UOM | D9: Freeish Region | E9: ='Distance Cost Calculator'!O16 -> 28 | G9: Sanbi | H9: 0 | I9: =($G$3*I$4)+$H9 -> 1 | J9: =($G$3*J$4)+$H9 -> 10 | K9: =($G$3*K$4)+$H9 -> 1.3 | L9: =($G$3*L$4)+$H9 -> 1.4 | N9: Sanbi | O9: 0 | P9: =($N$3*P$4)+$O9 -> 45 | R9: Sanbi | S9: 0 | T9: =U9*2 -> 6 | U9: =($R$3*U$4)+$S9 -> 3 | V9: =($R$3*V$4)+$S9 -> 28.5 | W9: =($R$3*W$4)+$S9 -> 4.5 | X9: =($R$3*X$4)+$S9 -> 5.25 | AA9: Sanbi | AB9: 0 | AC9: =($AA$3*AC$4)+$AB9 -> 20 | AD9: =($AA$3*AD$4)+$AB9 -> 26 | AF9: Sanbi | AG9: 0 | AH9: =($AF$3*AH$4)+$AG9 -> 1 | AI9: =($AF$3*AI$4)+$AG9 -> 3.1 | AJ9: =($AF$3*AJ$4)+$AG9 -> 3.5 | AK9: =($AF$3*AK$4)+$AG9 -> 3.4 | AL9: =($AF$3*AL$4)+$AG9 -> 4.2 | AO9: Sanbi | AP9: =$E$5 -> 17 | AQ9: =($AO$3*AQ$4)+$AP9 -> 142 | AS9: Sanbi | AT9: =$E$5 -> 17 | AU9: =($AS$3*AU$4)+$AT9 -> 19 | AV9: =($AS$3*AV$4)+$AT9 -> 21.2 | AW9: =($AS$3*AW$4)+$AT9 -> 23 | AX9: =($AS$3*AX$4)+$AT9 -> 20
A10: Calculator Weight | D10: Sanbi Region | E10: ='Distance Cost Calculator'!O17 -> 25 | R10: *Often available at lower, or multiple fruits for the same price.
A11: ='Distance Cost Calculator'!B14 -> 1 | B11: kg | D11: Tolerideme Region | E11: ='Distance Cost Calculator'!O18 -> 34
A12: *DO NOT CHANGE HERE* | D12: Sanbi Region (Tier I Avg) | G12: Siguash | N12: Steen | R12: Rakuja | AA12: Tastyleaf | AF12: Domar Carbey | AO12: Panita | AS12: Lolish
D13: Route | E13: Cost (Pearls) | G13: 2 | H13: Shipping | I13: Berries | J13: Dried | K13: Juice | L13: Hard Juice | N13: 34 | O13: Shipping | P13: Leaves | R13: 14 | S13: Shipping | T13: Single Fruit | U13: Fruit | V13: Dried | W13: Juice | X13: Hard Juice | AA13: 25 | AB13: Shipping | AC13: Tree core | AF13: 2 | AG13: Shipping | AH13: RAW | AI13: Flour | AJ13: Bread | AK13: Beer | AL13: Ale | AO13: 200 | AP13: Shipping | AQ13: Caps | AS13: 15 | AT13: Shipping | AU13: RAW | AV13: Hard Juice
D14: Freeish Region | E14: ='Distance Cost Calculator'!G21 -> 17 | G14: %Change | I14: 1 | J14: 10 | K14: 1.3 | L14: 1.4 | N14: %Change | P14: 1 | R14: %Change | T14: ~8cm | U14: 1 | V14: 9.84 | W14: 1.5 | X14: 1.85 | AA14: %Change | AC14: 1 | AF14: %Change | AH14: 1 | AI14: 3.1 | AJ14: 3.5 | AK14: 3.4 | AL14: 4.2 | AO14: %Change | AQ14: 1 | AS14: %Change | AU14: 1 | AV14: 1.2
D15: Gandew Region | E15: ='Distance Cost Calculator'!G22 -> 25 | G15: UOM | H15: Kg | I15: Kg | J15: Kg | K15: L | L15: L | N15: UOM | O15: Kg | P15: Kg | R15: UOM | S15: Kg | T15: ~70g - 75% Edible | U15: Kg | V15: Kg | W15: L | X15: L | AA15: UOM | AB15: Kg | AC15: Kg | AD15: Kg | AF15: UOM | AG15: Kg | AH15: Kg | AI15: Kg | AJ15: Kg | AK15: L | AL15: L | AO15: UOM | AP15: Kg | AQ15: Kg | AS15: UOM | AT15: Kg | AU15: Kg | AV15: L
D16: Tolerideme Region | E16: ='Distance Cost Calculator'!G23 -> 9 | G16: Freeish | H16: 0 | I16: =($G$13*I$14)+$H16 -> 2 | J16: =($G$13*J$14)+$H16 -> 20 | K16: =($G$13*K$14)+$H16 -> 2.6 | L16: =($G$13*L$14)+$H16 -> 2.8 | N16: Freeish | O16: 0 | P16: =($N$13*P$14)+$O16 -> 34 | R16: Freeish | S16: =$E$9 -> 28 | T16: =U16*0.07 -> 2.94 | U16: =($R$13*U$14)+$S16 -> 42 | V16: =($R$13*V$14)+$S16 -> 165.76 | W16: =($R$13*W$14)+$S16 -> 49 | X16: =($R$13*X$14)+$S16 -> 53.9 | AA16: Freeish | AB16: =$E$14 -> 17 | AC16: =($AA$13*AC$14)+$AB16 -> 42 | AD16: =($AA$13*AD$14)+$AB16 -> 17 | AF16: Freeish | AG16: =$E$19 -> 25 | AH16: =($AF$13*AH$14)+$AG16 -> 27 | AI16: =($AF$13*AI$14)+$AG16 -> 31.2 | AJ16: =($AF$13*AJ$14)+$AG16 -> 32 | AK16: =($AF$13*AK$14)+$AG16 -> 31.8 | AL16: =($AF$13*AL$14)+$AG16 -> 33.4 | AO16: Freeish | AP16: 0 | AQ16: =($AO$13*AQ$14)+$AP16 -> 200 | AS16: Freeish | AT16: =$E$9 -> 28 | AU16: =($AS$13*AU$14)+$AT16 -> 43 | AV16: =($AS$13*AV$14)+$AT16 -> 46
D17: Tolerideme Region (Tier I Avg) | G17: Gandew | H17: =$E$4 -> 28 | I17: =($G$13*I$14)+$H17 -> 30 | J17: =($G$13*J$14)+$H17 -> 48 | K17: =($G$13*K$14)+$H17 -> 30.6 | L17: =($G$13*L$14)+$H17 -> 30.8 | N17: Gandew | O17: =$E$4 -> 28 | P17: =($N$13*P$14)+$O17 -> 62 | R17: Gandew | S17: 0 | T17: =U17*0.07 -> 0.98 | U17: =($R$13*U$14)+$S17 -> 14 | V17: =($R$13*V$14)+$S17 -> 137.76 | W17: =($R$13*W$14)+$S17 -> 21 | X17: =($R$13*X$14)+$S17 -> 25.9 | AA17: Gandew | AB17: =$E$15 -> 25 | AC17: =($AA$13*AC$14)+$AB17 -> 50 | AD17: =($AA$13*AD$14)+$AB17 -> 25 | AF17: Gandew | AG17: =$E$20 -> 34 | AH17: =($AF$13*AH$14)+$AG17 -> 36 | AI17: =($AF$13*AI$14)+$AG17 -> 40.2 | AJ17: =($AF$13*AJ$14)+$AG17 -> 41 | AK17: =($AF$13*AK$14)+$AG17 -> 40.8 | AL17: =($AF$13*AL$14)+$AG17 -> 42.4 | AO17: Gandew | AP17: =$E$4 -> 28 | AQ17: =($AO$13*AQ$14)+$AP17 -> 228 | AS17: Gandew | AT17: 0 | AU17: =($AS$13*AU$14)+$AT17 -> 15 | AV17: =($AS$13*AV$14)+$AT17 -> 18
D18: Route | E18: Cost (Pearls) | G18: Tolerideme | H18: =$E$6 -> 25 | I18: =($G$13*I$14)+$H18 -> 27 | J18: =($G$13*J$14)+$H18 -> 45 | K18: =($G$13*K$14)+$H18 -> 27.6 | L18: =($G$13*L$14)+$H18 -> 27.8 | N18: Tolerideme | O18: =$E$16 -> 9 | P18: =($N$13*P$14)+$O18 -> 43 | R18: Tolerideme | S18: =$E$11 -> 34 | T18: =U18*0.07 -> 3.36 | U18: =($R$13*U$14)+$S18 -> 48 | V18: =($R$13*V$14)+$S18 -> 171.76 | W18: =($R$13*W$14)+$S18 -> 55 | X18: =($R$13*X$14)+$S18 -> 59.9 | AA18: Tolerideme | AB18: =$E$16 -> 9 | AC18: =($AA$13*AC$14)+$AB18 -> 34 | AD18: =($AA$13*AD$14)+$AB18 -> 9 | AF18: Tolerideme | AG18: 0 | AH18: =($AF$13*AH$14)+$AG18 -> 2 | AI18: =($AF$13*AI$14)+$AG18 -> 6.2 | AJ18: =($AF$13*AJ$14)+$AG18 -> 7 | AK18: =($AF$13*AK$14)+$AG18 -> 6.8 | AL18: =($AF$13*AL$14)+$AG18 -> 8.4 | AO18: Tolerideme | AP18: =$E$6 -> 25 | AQ18: =($AO$13*AQ$14)+$AP18 -> 225 | AS18: Tolerideme | AT18: =$E$11 -> 34 | AU18: =($AS$13*AU$14)+$AT18 -> 49 | AV18: =($AS$13*AV$14)+$AT18 -> 52
D19: Freeish Region | E19: ='Distance Cost Calculator'!O21 -> 25 | G19: Sanbi | H19: 0 | I19: =($G$13*I$14)+$H19 -> 2 | J19: =($G$13*J$14)+$H19 -> 20 | K19: =($G$13*K$14)+$H19 -> 2.6 | L19: =($G$13*L$14)+$H19 -> 2.8 | N19: Sanbi | O19: 0 | P19: =($N$13*P$14)+$O19 -> 34 | R19: Sanbi | S19: =$E$10 -> 25 | T19: =U19*0.07 -> 2.73 | U19: =($R$13*U$14)+$S19 -> 39 | V19: =($R$13*V$14)+$S19 -> 162.76 | W19: =($R$13*W$14)+$S19 -> 46 | X19: =($R$13*X$14)+$S19 -> 50.9 | AA19: Sanbi | AB19: 0 | AC19: =($AA$13*AC$14)+$AB19 -> 25 | AD19: =($AA$13*AD$14)+$AB19 -> 0 | AF19: Sanbi | AG19: =$E$21 -> 9 | AH19: =($AF$13*AH$14)+$AG19 -> 11 | AI19: =($AF$13*AI$14)+$AG19 -> 15.2 | AJ19: =($AF$13*AJ$14)+$AG19 -> 16 | AK19: =($AF$13*AK$14)+$AG19 -> 15.8 | AL19: =($AF$13*AL$14)+$AG19 -> 17.4 | AO19: Sanbi | AP19: =$E$5 -> 17 | AQ19: =($AO$13*AQ$14)+$AP19 -> 217 | AS19: Sanbi | AT19: =$E$10 -> 25 | AU19: =($AS$13*AU$14)+$AT19 -> 40 | AV19: =($AS$13*AV$14)+$AT19 -> 43
D20: Gandew Region | E20: ='Distance Cost Calculator'!O22 -> 34
D21: Sanbi Region | E21: ='Distance Cost Calculator'!O23 -> 9
G22: Basi | N22: Tibou | R22: Gosutam | AF22: Lehuj | AO22: Tyr
G23: 3 | H23: Shipping | I23: Berries | J23: Pulp | N23: 13 | O23: Shipping | P23: Flowers | R23: 9 | S23: Shipping | T23: Single Fruit | U23: Fruit | V23: Dried | W23: Juice | X23: Hard Juice | AF23: 1 | AG23: Shipping | AH23: RAW | AO23: 175 | AP23: Shipping | AQ23: Caps
G24: %Change | I24: 1 | J24: 2 | N24: %Change | P24: 1 | R24: %Change | T24: ~7cm | U24: 1 | V24: 9.25 | W24: 1.3 | X24: 1.45 | AF24: %Change | AH24: 1 | AO24: %Change | AQ24: 1
G25: UOM | H25: Kg | I25: Kg | J25: L | N25: UOM | O25: Kg | P25: Kg | R25: UOM | S25: Kg | T25: ~100g - 50% Edible | U25: Kg | V25: Kg | W25: L | X25: L | AF25: UOM | AG25: Kg | AH25: Kg | AO25: UOM | AP25: Kg | AQ25: Kg
G26: Freeish | H26: 0 | I26: =($G$23*I$24)+$H26 -> 3 | J26: =($G$23*J$24)+$H26 -> 6 | K26: =($G$23*K$24)+$H26 -> 0 | L26: =($G$23*L$24)+$H26 -> 0 | N26: Freeish | O26: =$E$14 -> 17 | P26: =($N$23*P$24)+$O26 -> 30 | R26: Freeish | S26: 0 | T26: =U26*0.1 -> 0.9 | U26: =($R$23*U$24)+$S26 -> 9 | V26: =($R$23*V$24)+$S26 -> 83.25 | W26: =($R$23*W$24)+$S26 -> 11.7 | X26: =($R$23*X$24)+$S26 -> 13.05 | AF26: Freeish | AG26: =$E$19 -> 25 | AH26: =($AF$23*AH$24)+$AG26 -> 26 | AO26: Freeish | AP26: 0 | AQ26: =($AO$23*AQ$24)+$AP26 -> 175
G27: Gandew | H27: =$E$4 -> 28 | I27: =($G$23*I$24)+$H27 -> 31 | J27: =($G$23*J$24)+$H27 -> 34 | K27: =($G$23*K$24)+$H27 -> 28 | L27: =($G$23*L$24)+$H27 -> 28 | N27: Gandew | O27: =$E$15 -> 25 | P27: =($N$23*P$24)+$O27 -> 38 | R27: Gandew | S27: =$E$4 -> 28 | T27: =U27*0.1 -> 3.7 | U27: =($R$23*U$24)+$S27 -> 37 | V27: =($R$23*V$24)+$S27 -> 111.25 | W27: =($R$23*W$24)+$S27 -> 39.7 | X27: =($R$23*X$24)+$S27 -> 41.05 | AF27: Gandew | AG27: =$E$20 -> 34 | AH27: =($AF$23*AH$24)+$AG27 -> 35 | AO27: Gandew | AP27: =$E$4 -> 28 | AQ27: =($AO$23*AQ$24)+$AP27 -> 203
G28: Tolerideme | H28: =$E$6 -> 25 | I28: =($G$23*I$24)+$H28 -> 28 | J28: =($G$23*J$24)+$H28 -> 31 | K28: =($G$23*K$24)+$H28 -> 25 | L28: =($G$23*L$24)+$H28 -> 25 | N28: Tolerideme | O28: =$E$16 -> 9 | P28: =($N$23*P$24)+$O28 -> 22 | R28: Tolerideme | S28: =$E$16 -> 9 | T28: =U28*0.1 -> 1.8 | U28: =($R$23*U$24)+$S28 -> 18 | V28: =($R$23*V$24)+$S28 -> 92.25 | W28: =($R$23*W$24)+$S28 -> 20.7 | X28: =($R$23*X$24)+$S28 -> 22.05 | AF28: Tolerideme | AG28: 0 | AH28: =($AF$23*AH$24)+$AG28 -> 1 | AO28: Tolerideme | AP28: =$E$6 -> 25 | AQ28: =($AO$23*AQ$24)+$AP28 -> 200
G29: Sanbi | H29: 0 | I29: =($G$23*I$24)+$H29 -> 3 | J29: =($G$23*J$24)+$H29 -> 6 | K29: =($G$23*K$24)+$H29 -> 0 | L29: =($G$23*L$24)+$H29 -> 0 | N29: Sanbi | O29: 0 | P29: =($N$23*P$24)+$O29 -> 13 | R29: Sanbi | S29: 0 | T29: =U29*0.1 -> 0.9 | U29: =($R$23*U$24)+$S29 -> 9 | V29: =($R$23*V$24)+$S29 -> 83.25 | W29: =($R$23*W$24)+$S29 -> 11.7 | X29: =($R$23*X$24)+$S29 -> 13.05 | AF29: Sanbi | AG29: =$E$21 -> 9 | AH29: =($AF$23*AH$24)+$AG29 -> 10 | AO29: Sanbi | AP29: =$E$5 -> 17 | AQ29: =($AO$23*AQ$24)+$AP29 -> 192
N32: Magina | R32: Yabuca
N33: 67 | O33: Shipping | P33: Flowers | R33: 6 | S33: Shipping | T33: Single Fruit | U33: Fruit | V33: Dried | W33: Juice | X33: Hard Juice
N34: %Change | P34: 1 | R34: %Change | T34: ~11cm | U34: 1 | V34: 8.75 | W34: 1.78 | X34: 2.04
N35: UOM | O35: Kg | P35: Kg | R35: UOM | S35: Kg | T35: ~330g - 80% Edible | U35: Kg | V35: Kg | W35: L | X35: L
N36: Freeish | O36: 0 | P36: =($N$33*P$34)+$O36 -> 67 | R36: Freeish | S36: 0 | T36: =U36*0.33 -> 1.98 | U36: =($R$33*U$34)+$S36 -> 6 | V36: =($R$33*V$34)+$S36 -> 52.5 | W36: =($R$33*W$34)+$S36 -> 10.68 | X36: =($R$33*X$34)+$S36 -> 12.24
N37: Gandew | O37: =$E$4 -> 28 | P37: =($N$33*P$34)+$O37 -> 95 | R37: Gandew | S37: =$E$4 -> 28 | T37: =U37*0.33 -> 11.22 | U37: =($R$33*U$34)+$S37 -> 34 | V37: =($R$33*V$34)+$S37 -> 80.5 | W37: =($R$33*W$34)+$S37 -> 38.68 | X37: =($R$33*X$34)+$S37 -> 40.24
N38: Tolerideme | O38: =$E$16 -> 9 | P38: =($N$33*P$34)+$O38 -> 76 | R38: Tolerideme | S38: =$E$6 -> 25 | T38: =U38*0.33 -> 10.23 | U38: =($R$33*U$34)+$S38 -> 31 | V38: =($R$33*V$34)+$S38 -> 77.5 | W38: =($R$33*W$34)+$S38 -> 35.68 | X38: =($R$33*X$34)+$S38 -> 37.24
N39: Sanbi | O39: 0 | P39: =($N$33*P$34)+$O39 -> 67 | R39: Sanbi | S39: =$E$5 -> 17 | T39: =U39*0.33 -> 7.59 | U39: =($R$33*U$34)+$S39 -> 23 | V39: =($R$33*V$34)+$S39 -> 69.5 | W39: =($R$33*W$34)+$S39 -> 27.68 | X39: =($R$33*X$34)+$S39 -> 29.24
N42: Nica | R42: Wood Yabuca
N43: 9 | O43: Shipping | P43: Seeds | R43: 12 | S43: Shipping | T43: Single Fruit | U43: Fruit | V43: Dried | W43: Juice | X43: Hard Juice
N44: %Change | P44: 1 | R44: %Change | T44: ~11cm | U44: 1 | V44: 8.75 | W44: 1.78 | X44: 2.04
N45: UOM | O45: Kg | P45: Kg | R45: UOM | S45: Kg | T45: ~330g - 80% Edible | U45: Kg | V45: Kg | W45: L | X45: L
N46: Freeish | O46: 0 | P46: =($N$43*P$44)+$O46 -> 9 | R46: Freeish | S46: =$E$19 -> 25 | T46: =U46*0.33 -> 12.21 | U46: =($R$43*U$44)+$S46 -> 37 | V46: =($R$43*V$44)+$S46 -> 130 | W46: =($R$43*W$44)+$S46 -> 46.36 | X46: =($R$43*X$44)+$S46 -> 49.48
N47: Gandew | O47: =$E$4 -> 28 | P47: =($N$43*P$44)+$O47 -> 37 | R47: Gandew | S47: =$E$20 -> 34 | T47: =U47*0.33 -> 15.18 | U47: =($R$43*U$44)+$S47 -> 46 | V47: =($R$43*V$44)+$S47 -> 139 | W47: =($R$43*W$44)+$S47 -> 55.36 | X47: =($R$43*X$44)+$S47 -> 58.48
N48: Tolerideme | O48: =$E$16 -> 9 | P48: =($N$43*P$44)+$O48 -> 18 | R48: Tolerideme | S48: 0 | T48: =U48*0.33 -> 3.96 | U48: =($R$43*U$44)+$S48 -> 12 | V48: =($R$43*V$44)+$S48 -> 105 | W48: =($R$43*W$44)+$S48 -> 21.36 | X48: =($R$43*X$44)+$S48 -> 24.48
N49: Sanbi | O49: 0 | P49: =($N$43*P$44)+$O49 -> 9 | R49: Sanbi | S49: =$E$21 -> 9 | T49: =U49*0.33 -> 6.93 | U49: =($R$43*U$44)+$S49 -> 21 | V49: =($R$43*V$44)+$S49 -> 114 | W49: =($R$43*W$44)+$S49 -> 30.36 | X49: =($R$43*X$44)+$S49 -> 33.48
R52: Hifuna Yabuca
R53: 53 | S53: Shipping | T53: Single Fruit | U53: Fruit | V53: Concentrated J
R54: %Change | T54: ~11cm | U54: 1 | V54: 5.18
R55: UOM | S55: Kg | T55: ~330g - 80% Edible | U55: Kg | V55: L
R56: Freeish | S56: =$E$19 -> 25 | T56: =U56*0.33 -> 25.74 | U56: =($R$53*U$54)+$S56 -> 78 | V56: =($R$53*V$54)+$S56 -> 299.54
R57: Gandew | S57: =$E$20 -> 34 | T57: =U57*0.33 -> 28.71 | U57: =($R$53*U$54)+$S57 -> 87 | V57: =($R$53*V$54)+$S57 -> 308.54
R58: Tolerideme | S58: 0 | T58: =U58*0.33 -> 17.49 | U58: =($R$53*U$54)+$S58 -> 53 | V58: =($R$53*V$54)+$S58 -> 274.54
R59: Sanbi | S59: =$E$21 -> 9 | T59: =U59*0.33 -> 20.46 | U59: =($R$53*U$54)+$S59 -> 62 | V59: =($R$53*V$54)+$S59 -> 283.54
R62: Purplebread
R63: 18 | S63: Shipping | T63: Single Fruit | U63: Fruit | V63: Dried | W63: Juice | X63: Hard Juice
R64: %Change | T64: ~11cm | U64: 1 | V64: 8.5 | W64: 1.5 | X64: 1.7
R65: UOM | S65: Kg | T65: ~200g - 47% Edible | U65: Kg | V65: Kg | W65: L | X65: L
R66: Freeish | S66: =$E$9 -> 28 | T66: =U66*0.2 -> 9.2 | U66: =($R$63*U$64)+$S66 -> 46 | V66: =($R$63*V$64)+$S66 -> 181 | W66: =($R$63*W$64)+$S66 -> 55 | X66: =($R$63*X$64)+$S66 -> 58.6
R67: Gandew | S67: 0 | T67: =U67*0.2 -> 3.6 | U67: =($R$63*U$64)+$S67 -> 18 | V67: =($R$63*V$64)+$S67 -> 153 | W67: =($R$63*W$64)+$S67 -> 27 | X67: =($R$63*X$64)+$S67 -> 30.6
R68: Tolerideme | S68: =$E$11 -> 34 | T68: =U68*0.2 -> 10.4 | U68: =($R$63*U$64)+$S68 -> 52 | V68: =($R$63*V$64)+$S68 -> 187 | W68: =($R$63*W$64)+$S68 -> 61 | X68: =($R$63*X$64)+$S68 -> 64.6
R69: Sanbi | S69: =$E$10 -> 25 | T69: =U69*0.2 -> 8.6 | U69: =($R$63*U$64)+$S69 -> 43 | V69: =($R$63*V$64)+$S69 -> 178 | W69: =($R$63*W$64)+$S69 -> 52 | X69: =($R$63*X$64)+$S69 -> 55.6
R72: Greenbread
R73: 1 | S73: Shipping | T73: Single Fruit | U73: Fruit | V73: Dried | W73: Juice | X73: Hard Juice | Y73: Roasted Beans
R74: %Change | T74: ~Human Size | U74: 1 | V74: 8.75 | W74: 2.15 | X74: 2.45 | Y74: 2.75
R75: UOM | S75: Kg | T75: ~80kg - 78% Edible | U75: Kg | V75: Kg | W75: L | X75: L | Y75: Kg
R76: Freeish | S76: 0 | T76: =U76*80 -> 80 | U76: =($R$73*U$74)+$S76 -> 1 | V76: =($R$73*V$74)+$S76 -> 8.75 | W76: =($R$73*W$74)+$S76 -> 2.15 | X76: =($R$73*X$74)+$S76 -> 2.45 | Y76: =($R$73*Y$74)+$S76 -> 2.75
R77: Gandew | S77: =$E$4 -> 28 | T77: =U77*80 -> 2320 | U77: =($R$73*U$74)+$S77 -> 29 | V77: =($R$73*V$74)+$S77 -> 36.75 | W77: =($R$73*W$74)+$S77 -> 30.15 | X77: =($R$73*X$74)+$S77 -> 30.45 | Y77: =($R$73*Y$74)+$S77 -> 30.75
R78: Tolerideme | S78: =$E$6 -> 25 | T78: =U78*80 -> 2080 | U78: =($R$73*U$74)+$S78 -> 26 | V78: =($R$73*V$74)+$S78 -> 33.75 | W78: =($R$73*W$74)+$S78 -> 27.15 | X78: =($R$73*X$74)+$S78 -> 27.45 | Y78: =($R$73*Y$74)+$S78 -> 27.75
R79: Sanbi | S79: =$E$5 -> 17 | T79: =U79*80 -> 1440 | U79: =($R$73*U$74)+$S79 -> 18 | V79: =($R$73*V$74)+$S79 -> 25.75 | W79: =($R$73*W$74)+$S79 -> 19.15 | X79: =($R$73*X$74)+$S79 -> 19.45 | Y79: =($R$73*Y$74)+$S79 -> 19.75
R82: Tenderthrough
R83: 4 | S83: Shipping | T83: Single Fruit | U83: Fruit | V83: Dried | W83: Juice | X83: Hard Juice | Y83: Dried Seeds
R84: %Change | T84: ~18cm | U84: 1 | V84: 9.5 | W84: 1.3 | X84: 1.49 | Y84: 2.85
R85: UOM | S85: Kg | T85: ~500g - 80% Edible | U85: Kg | V85: Kg | W85: L | X85: L | Y85: Kg
R86: Freeish | S86: 0 | T86: =U86*0.5 -> 2 | U86: =($R$83*U$84)+$S86 -> 4 | V86: =($R$83*V$84)+$S86 -> 38 | W86: =($R$83*W$84)+$S86 -> 5.2 | X86: =($R$83*X$84)+$S86 -> 5.96 | Y86: =($R$83*Y$84)+$S86 -> 11.4
R87: Gandew | S87: =$E$4 -> 28 | T87: =U87*0.5 -> 16 | U87: =($R$83*U$84)+$S87 -> 32 | V87: =($R$83*V$84)+$S87 -> 66 | W87: =($R$83*W$84)+$S87 -> 33.2 | X87: =($R$83*X$84)+$S87 -> 33.96 | Y87: =($R$83*Y$84)+$S87 -> 39.4
R88: Tolerideme | S88: =$E$16 -> 9 | T88: =U88*0.5 -> 6.5 | U88: =($R$83*U$84)+$S88 -> 13 | V88: =($R$83*V$84)+$S88 -> 47 | W88: =($R$83*W$84)+$S88 -> 14.2 | X88: =($R$83*X$84)+$S88 -> 14.96 | Y88: =($R$83*Y$84)+$S88 -> 20.4
R89: Sanbi | S89: 0 | T89: =U89*0.5 -> 2 | U89: =($R$83*U$84)+$S89 -> 4 | V89: =($R$83*V$84)+$S89 -> 38 | W89: =($R$83*W$84)+$S89 -> 5.2 | X89: =($R$83*X$84)+$S89 -> 5.96 | Y89: =($R$83*Y$84)+$S89 -> 11.4
R92: Lonllow
R93: 10 | S93: Shipping | T93: Single Fruit | U93: Fruit | V93: Dried | W93: Juice | X93: Hard Juice | Y93: Dried Seeds
R94: %Change | T94: ~9cm | U94: 1 | V94: 9.5 | W94: 1.3 | X94: 1.45 | Y94: 2.85
R95: UOM | S95: Kg | T95: ~150g - 90% Edible | U95: Kg | V95: Kg | W95: L | X95: L | Y95: Kg
R96: Freeish | S96: =$E$14 -> 17 | T96: =U96*0.2 -> 5.4 | U96: =($R$93*U$94)+$S96 -> 27 | V96: =($R$93*V$94)+$S96 -> 112 | W96: =($R$93*W$94)+$S96 -> 30 | X96: =($R$93*X$94)+$S96 -> 31.5 | Y96: =($R$93*Y$94)+$S96 -> 45.5
R97: Gandew | S97: =$E$15 -> 25 | T97: =U97*0.2 -> 7 | U97: =($R$93*U$94)+$S97 -> 35 | V97: =($R$93*V$94)+$S97 -> 120 | W97: =($R$93*W$94)+$S97 -> 38 | X97: =($R$93*X$94)+$S97 -> 39.5 | Y97: =($R$93*Y$94)+$S97 -> 53.5
R98: Tolerideme | S98: =$E$16 -> 9 | T98: =U98*0.2 -> 3.8 | U98: =($R$93*U$94)+$S98 -> 19 | V98: =($R$93*V$94)+$S98 -> 104 | W98: =($R$93*W$94)+$S98 -> 22 | X98: =($R$93*X$94)+$S98 -> 23.5 | Y98: =($R$93*Y$94)+$S98 -> 37.5
R99: Sanbi | S99: 0 | T99: =U99*0.2 -> 2 | U99: =($R$93*U$94)+$S99 -> 10 | V99: =($R$93*V$94)+$S99 -> 95 | W99: =($R$93*W$94)+$S99 -> 13 | X99: =($R$93*X$94)+$S99 -> 14.5 | Y99: =($R$93*Y$94)+$S99 -> 28.5
R102: Buzeta
R103: 9 | S103: Shipping | T103: Single Fruit | U103: Fruit | V103: Dried | W103: Juice | X103: Hard Juice
R104: %Change | T104: ~9cm | U104: 1 | V104: 7.1 | W104: 1.21 | X104: 1.5
R105: UOM | S105: Kg | T105: ~150g - 80% Edible | U105: Kg | V105: Kg | W105: L | X105: L
R106: Freeish | S106: 0 | T106: =U106*0.15 -> 1.35 | U106: =($R$103*U$104)+$S106 -> 9 | V106: =($R$103*V$104)+$S106 -> 63.9 | W106: =($R$103*W$104)+$S106 -> 10.89 | X106: =($R$103*X$104)+$S106 -> 13.5
R107: Gandew | S107: =$E$4 -> 28 | T107: =U107*0.15 -> 5.55 | U107: =($R$103*U$104)+$S107 -> 37 | V107: =($R$103*V$24)+$S107 -> 111.25 | W107: =($R$103*W$104)+$S107 -> 38.89 | X107: =($R$103*X$104)+$S107 -> 41.5
R108: Tolerideme | S108: =$E$16 -> 9 | T108: =U108*0.15 -> 2.7 | U108: =($R$103*U$104)+$S108 -> 18 | V108: =($R$103*V$104)+$S108 -> 72.9 | W108: =($R$103*W$104)+$S108 -> 19.89 | X108: =($R$103*X$104)+$S108 -> 22.5
R109: Sanbi | S109: 0 | T109: =U109*0.15 -> 1.35 | U109: =($R$103*U$104)+$S109 -> 9 | V109: =($R$103*V$104)+$S109 -> 63.9 | W109: =($R$103*W$104)+$S109 -> 10.89 | X109: =($R$103*X$104)+$S109 -> 13.5

Sheet Ore Base Price Calculator
A1: Vars + Guide | G1: Mineral/Organic Resources Calculator | L1: Wood Resources Calculator | P1: Money Resources Calculator | T1: Rare Resources Calculator
A2: Region Color Guide | D2: Freeish Region (Tier II Avg) | G2: Coal | L2: Wood | P2: Pearl | T2: Walking Heart
A3: Comparative Advantage | D3: Route | E3: Cost (Pearls) | G3: 4 | H3: Shipping | I3: Prepared | L3: 3 | M3: Shipping | N3: Prepared | P3: 180 | Q3: Shipping | R3: Prepared | T3: 1500 | U3: Shipping | V3: Prepared
A4: From Freeish | D4: Gandew Region | E4: ='Distance Cost Calculator'!H16/'Distance Cost Calculator'!B14 -> 40 | G4: %Change | I4: 1.4 | L4: %Change | N4: 1.2 | P4: %Change | R4: 1.2 | T4: %Change | V4: 1.65
A5: From Gandew | D5: Sanbi Region | E5: ='Distance Cost Calculator'!H17/'Distance Cost Calculator'!B14 -> 24 | G5: UOM | H5: Kg | I5: Kg | L5: UOM | M5: Kg | N5: Kg | P5: UOM | Q5: Kg | R5: Kg | T5: UOM | U5: Kg | V5: Kg
A6: From Sanbi | D6: Tolerideme Region | E6: ='Distance Cost Calculator'!H18/'Distance Cost Calculator'!B14 -> 36 | G6: Freeish | H6: 0 | I6: =($G$3*I$4)+$H6 -> 5.6 | L6: Freeish | M6: 0 | N6: =($L$3*N$4)+$M6 -> 3.6 | P6: Freeish | Q6: =$E$14 -> 24 | R6: =($P$3*R$4)+$Q6 -> 240 | T6: Freeish | U6: 0 | V6: =($T$3*V$4)+$U6 -> 2475
A7: From Tolerideme | D7: Gandew Region (Tier II Avg) | G7: Gandew | H7: =$E$9 -> 40 | I7: =($G$3*I$4)+$H7 -> 45.6 | L7: Gandew | M7: =$E$9 -> 40 | N7: =($L$3*N$4)+$M7 -> 43.6 | P7: Gandew | Q7: =$E$15 -> 36 | R7: =($P$3*R$4)+$Q7 -> 252 | T7: Gandew | U7: =$E$9 -> 40 | V7: =($T$3*V$4)+$U7 -> 2515
A8: UOM Per 1kg | D8: Route | E8: Cost (Pearls) | G8: Tolerideme | H8: 0 | I8: =($G$3*I$4)+$H8 -> 5.6 | L8: Tolerideme | M8: =E21 -> 12 | N8: =($L$3*N$4)+$M8 -> 15.6 | P8: Tolerideme | Q8: =$E$16 -> 12 | R8: =($P$3*R$4)+$Q8 -> 228 | T8: Tolerideme | U8: =$E$6 -> 36 | V8: =($T$3*V$4)+$U8 -> 2511
A9: Manual UOM | D9: Freeish Region | E9: ='Distance Cost Calculator'!P16/'Distance Cost Calculator'!B14 -> 40 | G9: Sanbi | H9: 0 | I9: =($G$3*I$4)+$H9 -> 5.6 | L9: Sanbi | M9: 0 | N9: =($L$3*N$4)+$M9 -> 3.6 | P9: Sanbi | Q9: 0 | R9: =($P$3*R$4)+$Q9 -> 216 | T9: Sanbi | U9: =$E$5 -> 24 | V9: =($T$3*V$4)+$U9 -> 2499
A10: Calculator Weight | D10: Sanbi Region | E10: ='Distance Cost Calculator'!P17/'Distance Cost Calculator'!B14 -> 36
D11: Tolerideme Region | E11: ='Distance Cost Calculator'!P18/'Distance Cost Calculator'!B14 -> 48
D12: Sanbi Region (Tier II Avg) | G12: Iron/Steel Ore | L12: Bone Wood | P12: Amethyst | T12: Gold
D13: Route | E13: Cost (Pearls) | G13: 32 | H13: Shipping | I13: Iron Ingot | J13: Steel Ingot | L13: 22 | M13: Shipping | N13: Smelted | P13: 9000 | Q13: Shipping | R13: Prepared | T13: 12000 | U13: Shipping | V13: Prepared
D14: Freeish Region | E14: ='Distance Cost Calculator'!H21/'Distance Cost Calculator'!B14 -> 24 | G14: %Change | I14: 3.05 | J14: 4.5 | L14: %Change | N14: 2.05 | P14: %Change | R14: 1.2 | T14: %Change | V14: 1.2
D15: Gandew Region | E15: ='Distance Cost Calculator'!H22/'Distance Cost Calculator'!B14 -> 36 | G15: UOM | H15: Kg | I15: Kg | L15: UOM | M15: Kg | N15: Kg | P15: UOM | Q15: Kg | R15: Kg | T15: UOM | U15: Kg | V15: Kg
D16: Tolerideme Region | E16: ='Distance Cost Calculator'!H23/'Distance Cost Calculator'!B14 -> 12 | G16: Freeish | H16: 0 | I16: =($G$13*I$14)+$H16 -> 97.6 | J16: =($G$13*J$14)+$H16 -> 144 | L16: Freeish | M16: 0 | N16: =($L$13*(N$14-0.2))+$M16 -> 40.7 | P16: Freeish | Q16: 0 | R16: =($P$13*R$14)+$Q16 -> 10800 | T16: Freeish | U16: 0 | V16: =($T$13*V$14)+$U16 -> 14400
D17: Tolerideme Region (Tier II Avg) | G17: Gandew | H17: 0 | I17: =($G$13*I$14)+$H17 -> 97.6 | J17: =($G$13*J$14)+$H17 -> 144 | L17: Gandew | M17: =E4 -> 40 | N17: =($L$13*N$14)+$M17 -> 85.1 | P17: Gandew | Q17: 0 | R17: =($P$13*R$14)+$Q17 -> 10800 | T17: Gandew | U17: =$E$9 -> 40 | V17: =($T$13*V$14)+$U17 -> 14440
D18: Route | E18: Cost (Pearls) | G18: Tolerideme | H18: =E16 -> 12 | I18: =($G$13*I$14)+$H18 -> 109.6 | J18: =($G$13*J$14)+$H18 -> 156 | L18: Tolerideme | M18: =E6 -> 36 | N18: =($L$13*N$14)+$M18 -> 81.1 | P18: Tolerideme | Q18: =$E$20 -> 48 | R18: =($P$13*R$14)+$Q18 -> 10848 | T18: Tolerideme | U18: =$E$21 -> 12 | V18: =($T$13*V$14)+$U18 -> 14412
D19: Freeish Region | E19: ='Distance Cost Calculator'!P21/'Distance Cost Calculator'!B14 -> 36 | G19: Sanbi | H19: 0 | I19: =($G$13*I$14)+$H19 -> 97.6 | J19: =($G$13*J$14)+$H19 -> 144 | L19: Sanbi | M19: =E5 -> 24 | N19: =($L$13*N$14)+$M19 -> 69.1 | P19: Sanbi | Q19: =$E$19 -> 36 | R19: =($P$13*R$14)+$Q19 -> 10836 | T19: Sanbi | U19: 0 | V19: =($T$13*V$14)+$U19 -> 14400
D20: Gandew Region | E20: ='Distance Cost Calculator'!P22/'Distance Cost Calculator'!B14 -> 48
D21: Sanbi Region | E21: ='Distance Cost Calculator'!P23/'Distance Cost Calculator'!B14 -> 12
G22: Chitin | L22: Soul Wood | P22: Aquamarine | T22: Diamond
G23: 22 | H23: Shipping | I23: Prepared | L23: 8 | M23: Shipping | N23: Prepared | P23: 90000 | Q23: Shipping | R23: Prepared | T23: 94000 | U23: Shipping | V23: Prepared
G24: %Change | I24: 1.2 | L24: %Change | N24: 1.35 | P24: %Change | R24: 1.2 | T24: %Change | V24: 1.2
G25: UOM | H25: Kg | I25: Kg | L25: UOM | M25: Kg | N25: Kg | P25: UOM | Q25: Kg | R25: Kg | T25: UOM | U25: Kg | V25: Kg
G26: Freeish | H26: =$E$9 -> 40 | I26: =($G$23*I$24)+$H26 -> 66.4 | L26: Freeish | M26: 0 | N26: =($L$23*N$24)+$M26 -> 10.8 | P26: Freeish | Q26: 0 | R26: =($P$23*R$24)+$Q26 -> 108000 | T26: Freeish | U26: 0 | V26: =($T$23*V$24)+$U26 -> 112800
G27: Gandew | H27: 0 | I27: =($G$23*I$24)+$H27 -> 26.4 | L27: Gandew | M27: =E4 -> 40 | N27: =($L$23*N$24)+$M27 -> 50.8 | P27: Gandew | Q27: 0 | R27: =($P$23*R$24)+$Q27 -> 108000 | T27: Gandew | U27: =$E$9 -> 40 | V27: =($T$23*V$24)+$U27 -> 112840
G28: Tolerideme | H28: =$E$11 -> 48 | I28: =($G$23*I$24)+$H28 -> 74.4 | L28: Tolerideme | M28: =E6 -> 36 | N28: =($L$23*N$24)+$M28 -> 46.8 | P28: Tolerideme | Q28: =$E$20 -> 48 | R28: =($P$23*R$24)+$Q28 -> 108048 | T28: Tolerideme | U28: =$E$21 -> 12 | V28: =($T$23*V$24)+$U28 -> 112812
G29: Sanbi | H29: =$E$10 -> 36 | I29: =($G$23*I$24)+$H29 -> 62.4 | L29: Sanbi | M29: =E5 -> 24 | N29: =($L$23*N$24)+$M29 -> 34.8 | P29: Sanbi | Q29: =$E$19 -> 36 | R29: =($P$23*R$24)+$Q29 -> 108036 | T29: Sanbi | U29: 0 | V29: =($T$23*V$24)+$U29 -> 112800
G32: Animal Hide/Leather | L32: Black Wood | P32: Sapphire
G33: 19 | H33: Shipping | I33: Prepared | L33: 23 | M33: Shipping | N33: Prepared | P33: 900000 | Q33: Shipping | R33: Prepared
G34: %Change | I34: 1.2 | L34: %Change | N34: 1.35 | P34: %Change | R34: 1.35
G35: UOM | H35: Kg | I35: Kg | L35: UOM | M35: Kg | N35: Kg | P35: UOM | Q35: Kg | R35: Kg
G36: Freeish | H36: 0 | I36: =($G$33*I$34)+$H36 -> 22.8 | L36: Freeish | M36: =$E$9 -> 40 | N36: =($L$33*N$34)+$M36 -> 71.05 | P36: Freeish | Q36: 0 | R36: =($P$33*R$34)+$Q36 -> 1215000
G37: Gandew | H37: =$E$9 -> 40 | I37: =($G$33*I$34)+$H37 -> 62.8 | L37: Gandew | M37: 0 | N37: =($L$33*N$34)+$M37 -> 31.05 | P37: Gandew | Q37: 0 | R37: =($P$33*R$34)+$Q37 -> 1215000
G38: Tolerideme | H38: =$E$16 -> 12 | I38: =($G$33*I$34)+$H38 -> 34.8 | L38: Tolerideme | M38: =$E$11 -> 48 | N38: =($L$33*N$34)+$M38 -> 79.05 | P38: Tolerideme | Q38: =$E$20 -> 48 | R38: =($P$33*R$34)+$Q38 -> 1215048
G39: Sanbi | H39: 0 | I39: =($G$33*(I$34-0.3))+$H39 -> 17.1 | L39: Sanbi | M39: =$E$10 -> 36 | N39: =($L$33*N$34)+$M39 -> 67.05 | P39: Sanbi | Q39: =$E$19 -> 36 | R39: =($P$33*R$34)+$Q39 -> 1215036
G42: Tibou
G43: ='Flora Base Price Calculator'!N23 -> 13 | H43: Shipping | I43: Prepared
G44: %Change | I44: 1.2
G45: UOM | H45: Kg | I45: Kg
G46: Freeish | H46: =$E$14 -> 24 | I46: =($G$43*I$44)+$H46 -> 39.6
G47: Gandew | H47: =$E$15 -> 36 | I47: =($G$43*I$44)+$H47 -> 51.6
G48: Tolerideme | H48: =$E$16 -> 12 | I48: =($G$43*I$44)+$H48 -> 27.6
G49: Sanbi | H49: 0 | I49: =($G$43*I$44)+$H49 -> 15.6
G52: Fost Stone
G53: 15 | H53: Shipping | I53: Prepared
G54: %Change | I54: 1.05
G55: UOM | H55: Kg | I55: Kg
G56: Freeish | H56: 0 | I56: =($G$53*I$54)+$H56 -> 15.75
G57: Gandew | H57: 0 | I57: =($G$53*I$54)+$H57 -> 15.75
G58: Tolerideme | H58: 0 | I58: =($G$53*I$54)+$H58 -> 15.75
G59: Sanbi | H59: 0 | I59: =($G$53*I$54)+$H59 -> 15.75
G62: Cooper
G63: 375 | H63: Shipping | I63: Prepared
G64: %Change | I64: 1.35
G65: UOM | H65: Kg | I65: Kg
G66: Freeish | H66: 0 | I66: =($G$63*I$64)+$H66 -> 506.25
G67: Gandew | H67: =$E$9 -> 40 | I67: =($G$63*I$64)+$H67 -> 546.25
G68: Tolerideme | H68: =$E$6 -> 36 | I68: =($G$63*I$64)+$H68 -> 542.25
G69: Sanbi | H69: =$E$5 -> 24 | I69: =($G$63*I$64)+$H69 -> 530.25

Sheet Equipment Price Calculator
A1: Vars + Guide | G1: Equipment | O1: Equipment | W1: Equipment | AE1: Graphs
A2: Region Color Guide | D2: Freeish Region (Tier II Avg) | G2: Helmet | O2: Full Set | W2: Freeish Avg Days Summary Table
A3: Comparative Advantage | D3: Route | E3: Cost (Pearls) | G3: 3 | H3: Iron | I3: Steel | J3: Bone Wood | K3: Chitin | L3: Tibou | M3: Leather | P3: Iron | Q3: Steel | R3: Bone Wood | S3: Chitin | T3: Tibou | U3: Leather | W3: Wage Tier | X3: Iron | Y3: Steel | Z3: Bone Wood | AA3: Chitin | AB3: Tibou | AC3: Leather
A4: From Freeish | D4: Gandew Region | E4: ='Distance Cost Calculator'!H16/'Distance Cost Calculator'!B14 -> 40 | G4: MATERIAL COST ALONE + SHIPPING. | O4: MATERIAL COST ALONE + SHIPPING. | W4: Tier I | X4: =P16 -> 439.2 | Y4: =Q16 -> 648 | Z4: =R16 -> 183.15 | AA4: =S16 -> 298.8 | AB4: =T16 -> 178.2 | AC4: =U16 -> 102.6
A5: From Gandew | D5: Sanbi Region | E5: ='Distance Cost Calculator'!H17/'Distance Cost Calculator'!B14 -> 24 | G5: UOM | H5: Unit | I5: Unit | J5: Unit | K5: Unit | L5: Unit | M5: Unit | O5: UOM | P5: Unit | Q5: Unit | R5: Unit | S5: Unit | T5: Unit | U5: Unit | W5: Tier II | X5: =P26 -> 146.4 | Y5: =Q26 -> 216 | Z5: =R26 -> 61.05 | AA5: =S26 -> 99.6 | AB5: =T26 -> 59.4 | AC5: =U26 -> 34.2
A6: From Sanbi | D6: Tolerideme Region | E6: ='Distance Cost Calculator'!H18/'Distance Cost Calculator'!B14 -> 36 | G6: Freeish | H6: ='Ore Base Price Calculator'!$I$16*$G$3 -> 292.8 | I6: ='Ore Base Price Calculator'!$J$16*$G$3 -> 432 | J6: ='Ore Base Price Calculator'!$N$16*$G$3 -> 122.1 | K6: ='Ore Base Price Calculator'!$I$26*$G$3 -> 199.2 | L6: ='Ore Base Price Calculator'!$I$46*$G$3 -> 118.8 | M6: ='Ore Base Price Calculator'!$I$36*$G$3 -> 68.4 | O6: Freeish | P6: =H6+H16+H26+H36 -> 2635.2 | Q6: =I6+I16+I26+I36 -> 3888 | R6: =J6+J16+J26+J36 -> 1098.9 | S6: =K6+K16+K26+K36 -> 1792.8 | T6: =L6+L16+L26+L36 -> 1069.2 | U6: =M6+M16+M26+M36 -> 615.6 | W6: Tier III | X6: =P36 -> 109.8 | Y6: =Q36 -> 162 | Z6: =R36 -> 45.7875 | AA6: =S36 -> 74.7 | AB6: =T36 -> 44.55 | AC6: =U36 -> 25.65
A7: From Tolerideme | D7: Gandew Region (Tier II Avg) | G7: Gandew | H7: ='Ore Base Price Calculator'!$I$17*$G$3 -> 292.8 | I7: ='Ore Base Price Calculator'!$J$17*$G$3 -> 432 | J7: ='Ore Base Price Calculator'!$N$17*$G$3 -> 255.3 | K7: ='Ore Base Price Calculator'!$I$27*$G$3 -> 79.2 | L7: ='Ore Base Price Calculator'!$I$47*$G$3 -> 154.8 | M7: ='Ore Base Price Calculator'!$I$37*$G$3 -> 188.4 | O7: Gandew | P7: =H7+H17+H27+H37 -> 2635.2 | Q7: =I7+I17+I27+I37 -> 3888 | R7: =J7+J17+J27+J37 -> 2297.7 | S7: =K7+K17+K27+K37 -> 712.8 | T7: =L7+L17+L27+L37 -> 1393.2 | U7: =M7+M17+M27+M37 -> 1695.6 | W7: Tier IV | X7: =P46 -> 73.2 | Y7: =Q46 -> 108 | Z7: =R46 -> 30.525 | AA7: =S46 -> 49.8 | AB7: =T46 -> 29.7 | AC7: =U46 -> 17.1
A8: UOM Per 1kg | D8: Route | E8: Cost (Pearls) | G8: Tolerideme | H8: ='Ore Base Price Calculator'!$I$18*$G$3 -> 328.8 | I8: ='Ore Base Price Calculator'!$J$18*$G$3 -> 468 | J8: ='Ore Base Price Calculator'!$N$18*$G$3 -> 243.3 | K8: ='Ore Base Price Calculator'!$I$28*$G$3 -> 223.2 | L8: ='Ore Base Price Calculator'!$I$48*$G$3 -> 82.8 | M8: ='Ore Base Price Calculator'!$I$38*$G$3 -> 104.4 | O8: Tolerideme | P8: =H8+H18+H28+H38 -> 2959.2 | Q8: =I8+I18+I28+I38 -> 4212 | R8: =J8+J18+J28+J38 -> 2189.7 | S8: =K8+K18+K28+K38 -> 2008.8 | T8: =L8+L18+L28+L38 -> 745.2 | U8: =M8+M18+M28+M38 -> 939.6
A9: Manual UOM | D9: Freeish Region | E9: ='Distance Cost Calculator'!P16/'Distance Cost Calculator'!B14 -> 40 | G9: Sanbi | H9: ='Ore Base Price Calculator'!$I$19*$G$3 -> 292.8 | I9: ='Ore Base Price Calculator'!$J$19*$G$3 -> 432 | J9: ='Ore Base Price Calculator'!$N$19*$G$3 -> 207.3 | K9: ='Ore Base Price Calculator'!$I$29*$G$3 -> 187.2 | L9: ='Ore Base Price Calculator'!$I$49*$G$3 -> 46.8 | M9: ='Ore Base Price Calculator'!$I$39*$G$3 -> 51.3 | O9: Sanbi | P9: =H9+H19+H29+H39 -> 2635.2 | Q9: =I9+I19+I29+I39 -> 3888 | R9: =J9+J19+J29+J39 -> 1865.7 | S9: =K9+K19+K29+K39 -> 1684.8 | T9: =L9+L19+L29+L39 -> 421.2 | U9: =M9+M19+M29+M39 -> 461.7
A10: Calculator Weight | D10: Sanbi Region | E10: ='Distance Cost Calculator'!P17/'Distance Cost Calculator'!B14 -> 36 | O10: Avg Cost in Amethyst | P10: =(((P9+P8+P7+P6)/4)/50) -> 54.324 | Q10: =(((Q9+Q8+Q7+Q6)/4)/50) -> 79.38 | R10: =(((R9+R8+R7+R6)/4)/50) -> 37.26 | S10: =(((S9+S8+S7+S6)/4)/50) -> 30.996 | T10: =(((T9+T8+T7+T6)/4)/50) -> 18.144 | U10: =(((U9+U8+U7+U6)/4)/50) -> 18.5625
D11: Tolerideme Region | E11: ='Distance Cost Calculator'!P18/'Distance Cost Calculator'!B14 -> 48
D12: Sanbi Region (Tier II Avg) | G12: Chest | O12: Full Set (Master level Work Days assuming 1/2 salary as savings) | W12: Gandew Avg Days Summary Table
D13: Route | E13: Cost (Pearls) | G13: 13 | H13: Iron | I13: Steel | J13: Bone Wood | K13: Chitin | L13: Tibou | M13: Leather | O13: Tier I | P13: Iron | Q13: Steel | R13: Bone Wood | S13: Chitin | T13: Tibou | U13: Leather | W13: Wage Tier | X13: Iron | Y13: Steel | Z13: Bone Wood | AA13: Chitin | AB13: Tibou | AC13: Leather
D14: Freeish Region | E14: ='Distance Cost Calculator'!H21/'Distance Cost Calculator'!B14 -> 24 | G14: MATERIAL COST ALONE + SHIPPING. | P14: Tier I | Q14: Tier I | R14: Tier I | S14: Tier I | T14: Tier I | U14: Tier I | W14: Tier I | X14: =P17 -> 439.2 | Y14: =Q17 -> 648 | Z14: =R17 -> 382.95 | AA14: =S17 -> 118.8 | AB14: =T17 -> 232.2 | AC14: =U17 -> 282.6
D15: Gandew Region | E15: ='Distance Cost Calculator'!H22/'Distance Cost Calculator'!B14 -> 36 | G15: UOM | H15: Unit | I15: Unit | J15: Unit | K15: Unit | L15: Unit | M15: Unit | O15: UOM | P15: Days | Q15: Days | R15: Days | S15: Days | T15: Days | U15: Days | W15: Tier II | X15: =P27 -> 146.4 | Y15: =Q27 -> 216 | Z15: =R27 -> 127.65 | AA15: =S27 -> 39.6 | AB15: =T27 -> 77.4 | AC15: =U27 -> 94.2
D16: Tolerideme Region | E16: ='Distance Cost Calculator'!H23/'Distance Cost Calculator'!B14 -> 12 | G16: Freeish | H16: ='Ore Base Price Calculator'!$I$16*$G$13 -> 1268.8 | I16: ='Ore Base Price Calculator'!$J$16*$G$13 -> 1872 | J16: ='Ore Base Price Calculator'!$N$16*$G$13 -> 529.1 | K16: ='Ore Base Price Calculator'!$I$26*$G$13 -> 863.2 | L16: ='Ore Base Price Calculator'!$I$46*$G$13 -> 514.8 | M16: ='Ore Base Price Calculator'!$I$36*$G$13 -> 296.4 | O16: Freeish | P16: =P$6/('Salary Calculator'!$B$10/2) -> 439.2 | Q16: =Q$6/('Salary Calculator'!$B$10/2) -> 648 | R16: =R$6/('Salary Calculator'!$B$10/2) -> 183.15 | S16: =S$6/('Salary Calculator'!$B$10/2) -> 298.8 | T16: =T$6/('Salary Calculator'!$B$10/2) -> 178.2 | U16: =U$6/('Salary Calculator'!$B$10/2) -> 102.6 | W16: Tier III | X16: =P37 -> 109.8 | Y16: =Q37 -> 162 | Z16: =R37 -> 95.7375 | AA16: =S37 -> 29.7 | AB16: =T37 -> 58.05 | AC16: =U37 -> 70.65
D17: Tolerideme Region (Tier II Avg) | G17: Gandew | H17: ='Ore Base Price Calculator'!$I$17*$G$13 -> 1268.8 | I17: ='Ore Base Price Calculator'!$J$17*$G$13 -> 1872 | J17: ='Ore Base Price Calculator'!$N$17*$G$13 -> 1106.3 | K17: ='Ore Base Price Calculator'!$I$27*$G$13 -> 343.2 | L17: ='Ore Base Price Calculator'!$I$47*$G$13 -> 670.8 | M17: ='Ore Base Price Calculator'!$I$37*$G$13 -> 816.4 | O17: Gandew | P17: =P$7/('Salary Calculator'!$B$10/2) -> 439.2 | Q17: =Q$7/('Salary Calculator'!$B$10/2) -> 648 | R17: =R$7/('Salary Calculator'!$B$10/2) -> 382.95 | S17: =S$7/('Salary Calculator'!$B$10/2) -> 118.8 | T17: =T$7/('Salary Calculator'!$B$10/2) -> 232.2 | U17: =U$7/('Salary Calculator'!$B$10/2) -> 282.6 | W17: Tier IV | X17: =P47 -> 73.2 | Y17: =Q47 -> 108 | Z17: =R47 -> 63.825 | AA17: =S47 -> 19.8 | AB17: =T47 -> 38.7 | AC17: =U47 -> 47.1
D18: Route | E18: Cost (Pearls) | G18: Tolerideme | H18: ='Ore Base Price Calculator'!$I$18*$G$13 -> 1424.8 | I18: ='Ore Base Price Calculator'!$J$18*$G$13 -> 2028 | J18: ='Ore Base Price Calculator'!$N$18*$G$13 -> 1054.3 | K18: ='Ore Base Price Calculator'!$I$28*$G$13 -> 967.2 | L18: ='Ore Base Price Calculator'!$I$48*$G$13 -> 358.8 | M18: ='Ore Base Price Calculator'!$I$38*$G$13 -> 452.4 | O18: Tolerideme | P18: =P$8/('Salary Calculator'!$B$10/2) -> 493.2 | Q18: =Q$8/('Salary Calculator'!$B$10/2) -> 702 | R18: =R$8/('Salary Calculator'!$B$10/2) -> 364.95 | S18: =S$8/('Salary Calculator'!$B$10/2) -> 334.8 | T18: =T$8/('Salary Calculator'!$B$10/2) -> 124.2 | U18: =U$8/('Salary Calculator'!$B$10/2) -> 156.6
D19: Freeish Region | E19: ='Distance Cost Calculator'!P21/'Distance Cost Calculator'!B14 -> 36 | G19: Sanbi | H19: ='Ore Base Price Calculator'!$I$19*$G$13 -> 1268.8 | I19: ='Ore Base Price Calculator'!$J$19*$G$13 -> 1872 | J19: ='Ore Base Price Calculator'!$N$19*$G$13 -> 898.3 | K19: ='Ore Base Price Calculator'!$I$29*$G$13 -> 811.2 | L19: ='Ore Base Price Calculator'!$I$49*$G$13 -> 202.8 | M19: ='Ore Base Price Calculator'!$I$39*$G$13 -> 222.3 | O19: Sanbi | P19: =P$9/('Salary Calculator'!$B$10/2) -> 439.2 | Q19: =Q$9/('Salary Calculator'!$B$10/2) -> 648 | R19: =R$9/('Salary Calculator'!$B$10/2) -> 310.95 | S19: =S$9/('Salary Calculator'!$B$10/2) -> 280.8 | T19: =T$9/('Salary Calculator'!$B$10/2) -> 70.2 | U19: =U$9/('Salary Calculator'!$B$10/2) -> 76.95
D20: Gandew Region | E20: ='Distance Cost Calculator'!P22/'Distance Cost Calculator'!B14 -> 48 | O20: Tier I Avg Days | P20: =(((P19+P18+P17+P16)/4)) -> 452.7 | Q20: =(((Q19+Q18+Q17+Q16)/4)) -> 661.5 | R20: =(((R19+R18+R17+R16)/4)) -> 310.5 | S20: =(((S19+S18+S17+S16)/4)) -> 258.3 | T20: =(((T19+T18+T17+T16)/4)) -> 151.2 | U20: =(((U19+U18+U17+U16)/4)) -> 154.6875
D21: Sanbi Region | E21: ='Distance Cost Calculator'!P23/'Distance Cost Calculator'!B14 -> 12
G22: Arm | O22: Full Set (Master level Work Days assuming 1/2 salary as savings) | W22: Tolerideme Avg Days Summary Table
G23: 5 | H23: Iron | I23: Steel | J23: Bone Wood | K23: Chitin | L23: Tibou | M23: Leather | P23: Iron | Q23: Steel | R23: Bone Wood | S23: Chitin | T23: Tibou | U23: Leather | W23: Wage Tier | X23: Iron | Y23: Steel | Z23: Bone Wood | AA23: Chitin | AB23: Tibou | AC23: Leather
G24: MATERIAL COST ALONE + SHIPPING. | P24: Tier II | Q24: Tier II | R24: Tier II | S24: Tier II | T24: Tier II | U24: Tier II | W24: Tier I | X24: =P18 -> 493.2 | Y24: =Q18 -> 702 | Z24: =R18 -> 364.95 | AA24: =S18 -> 334.8 | AB24: =T18 -> 124.2 | AC24: =U18 -> 156.6
G25: UOM | H25: Unit | I25: Unit | J25: Unit | K25: Unit | L25: Unit | M25: Unit | O25: UOM | P25: Days | Q25: Days | R25: Days | S25: Days | T25: Days | U25: Days | W25: Tier II | X25: =P28 -> 164.4 | Y25: =Q28 -> 234 | Z25: =R28 -> 121.65 | AA25: =S28 -> 111.6 | AB25: =T28 -> 41.4 | AC25: =U28 -> 52.2
G26: Freeish | H26: ='Ore Base Price Calculator'!$I$16*$G$23 -> 488 | I26: ='Ore Base Price Calculator'!$J$16*$G$23 -> 720 | J26: ='Ore Base Price Calculator'!$N$16*$G$23 -> 203.5 | K26: ='Ore Base Price Calculator'!$I$26*$G$23 -> 332 | L26: ='Ore Base Price Calculator'!$I$46*$G$23 -> 198 | M26: ='Ore Base Price Calculator'!$I$36*$G$23 -> 114 | O26: Freeish | P26: =P$6/('Salary Calculator'!$C$10/2) -> 146.4 | Q26: =Q$6/('Salary Calculator'!$C$10/2) -> 216 | R26: =R$6/('Salary Calculator'!$C$10/2) -> 61.05 | S26: =S$6/('Salary Calculator'!$C$10/2) -> 99.6 | T26: =T$6/('Salary Calculator'!$C$10/2) -> 59.4 | U26: =U$6/('Salary Calculator'!$C$10/2) -> 34.2 | W26: Tier III | X26: =P38 -> 123.3 | Y26: =Q38 -> 175.5 | Z26: =R38 -> 91.2375 | AA26: =S38 -> 83.7 | AB26: =T38 -> 31.05 | AC26: =U38 -> 39.15
G27: Gandew | H27: ='Ore Base Price Calculator'!$I$17*$G$23 -> 488 | I27: ='Ore Base Price Calculator'!$J$17*$G$23 -> 720 | J27: ='Ore Base Price Calculator'!$N$17*$G$23 -> 425.5 | K27: ='Ore Base Price Calculator'!$I$27*$G$23 -> 132 | L27: ='Ore Base Price Calculator'!$I$47*$G$23 -> 258 | M27: ='Ore Base Price Calculator'!$I$37*$G$23 -> 314 | O27: Gandew | P27: =P$7/('Salary Calculator'!$C$10/2) -> 146.4 | Q27: =Q$7/('Salary Calculator'!$C$10/2) -> 216 | R27: =R$7/('Salary Calculator'!$C$10/2) -> 127.65 | S27: =S$7/('Salary Calculator'!$C$10/2) -> 39.6 | T27: =T$7/('Salary Calculator'!$C$10/2) -> 77.4 | U27: =U$7/('Salary Calculator'!$C$10/2) -> 94.2 | W27: Tier IV | X27: =P48 -> 82.2 | Y27: =Q48 -> 117 | Z27: =R48 -> 60.825 | AA27: =S48 -> 55.8 | AB27: =T48 -> 20.7 | AC27: =U48 -> 26.1
G28: Tolerideme | H28: ='Ore Base Price Calculator'!$I$18*$G$23 -> 548 | I28: ='Ore Base Price Calculator'!$J$18*$G$23 -> 780 | J28: ='Ore Base Price Calculator'!$N$18*$G$23 -> 405.5 | K28: ='Ore Base Price Calculator'!$I$28*$G$23 -> 372 | L28: ='Ore Base Price Calculator'!$I$48*$G$23 -> 138 | M28: ='Ore Base Price Calculator'!$I$38*$G$23 -> 174 | O28: Tolerideme | P28: =P$8/('Salary Calculator'!$C$10/2) -> 164.4 | Q28: =Q$8/('Salary Calculator'!$C$10/2) -> 234 | R28: =R$8/('Salary Calculator'!$C$10/2) -> 121.65 | S28: =S$8/('Salary Calculator'!$C$10/2) -> 111.6 | T28: =T$8/('Salary Calculator'!$C$10/2) -> 41.4 | U28: =U$8/('Salary Calculator'!$C$10/2) -> 52.2
G29: Sanbi | H29: ='Ore Base Price Calculator'!$I$19*$G$23 -> 488 | I29: ='Ore Base Price Calculator'!$J$19*$G$23 -> 720 | J29: ='Ore Base Price Calculator'!$N$19*$G$23 -> 345.5 | K29: ='Ore Base Price Calculator'!$I$29*$G$23 -> 312 | L29: ='Ore Base Price Calculator'!$I$49*$G$23 -> 78 | M29: ='Ore Base Price Calculator'!$I$39*$G$23 -> 85.5 | O29: Sanbi | P29: =P$9/('Salary Calculator'!$C$10/2) -> 146.4 | Q29: =Q$9/('Salary Calculator'!$C$10/2) -> 216 | R29: =R$9/('Salary Calculator'!$C$10/2) -> 103.65 | S29: =S$9/('Salary Calculator'!$C$10/2) -> 93.6 | T29: =T$9/('Salary Calculator'!$C$10/2) -> 23.4 | U29: =U$9/('Salary Calculator'!$C$10/2) -> 25.65
O30: Tier II Avg Days | P30: =(((P29+P28+P27+P26)/4)) -> 150.9 | Q30: =(((Q29+Q28+Q27+Q26)/4)) -> 220.5 | R30: =(((R29+R28+R27+R26)/4)) -> 103.5 | S30: =(((S29+S28+S27+S26)/4)) -> 86.1 | T30: =(((T29+T28+T27+T26)/4)) -> 50.4 | U30: =(((U29+U28+U27+U26)/4)) -> 51.5625
G32: Leg | O32: Full Set (Master level Work Days assuming 1/2 salary as savings) | W32: Sanbi Avg Days Summary Table
G33: 6 | H33: Iron | I33: Steel | J33: Bone Wood | K33: Chitin | L33: Tibou | M33: Leather | P33: Iron | Q33: Steel | R33: Bone Wood | S33: Chitin | T33: Tibou | U33: Leather | W33: Wage Tier | X33: Iron | Y33: Steel | Z33: Bone Wood | AA33: Chitin | AB33: Tibou | AC33: Leather
G34: MATERIAL COST ALONE + SHIPPING. | P34: Tier III | Q34: Tier III | R34: Tier III | S34: Tier III | T34: Tier III | U34: Tier III | W34: Tier I | X34: =P19 -> 439.2 | Y34: =Q19 -> 648 | Z34: =R19 -> 310.95 | AA34: =S19 -> 280.8 | AB34: =T19 -> 70.2 | AC34: =U19 -> 76.95
G35: UOM | H35: Unit | I35: Unit | J35: Unit | K35: Unit | L35: Unit | M35: Unit | O35: UOM | P35: Days | Q35: Days | R35: Days | S35: Days | T35: Days | U35: Days | W35: Tier II | X35: =P29 -> 146.4 | Y35: =Q29 -> 216 | Z35: =R29 -> 103.65 | AA35: =S29 -> 93.6 | AB35: =T29 -> 23.4 | AC35: =U29 -> 25.65
G36: Freeish | H36: ='Ore Base Price Calculator'!$I$16*$G$33 -> 585.6 | I36: ='Ore Base Price Calculator'!$J$16*$G$33 -> 864 | J36: ='Ore Base Price Calculator'!$N$16*$G$33 -> 244.2 | K36: ='Ore Base Price Calculator'!$I$26*$G$33 -> 398.4 | L36: ='Ore Base Price Calculator'!$I$46*$G$33 -> 237.6 | M36: ='Ore Base Price Calculator'!$I$36*$G$33 -> 136.8 | O36: Freeish | P36: =P$6/('Salary Calculator'!$D$10/2) -> 109.8 | Q36: =Q$6/('Salary Calculator'!$D$10/2) -> 162 | R36: =R$6/('Salary Calculator'!$D$10/2) -> 45.7875 | S36: =S$6/('Salary Calculator'!$D$10/2) -> 74.7 | T36: =T$6/('Salary Calculator'!$D$10/2) -> 44.55 | U36: =U$6/('Salary Calculator'!$D$10/2) -> 25.65 | W36: Tier III | X36: =P39 -> 109.8 | Y36: =Q39 -> 162 | Z36: =R39 -> 77.7375 | AA36: =S39 -> 70.2 | AB36: =T39 -> 17.55 | AC36: =U39 -> 19.2375
G37: Gandew | H37: ='Ore Base Price Calculator'!$I$17*$G$33 -> 585.6 | I37: ='Ore Base Price Calculator'!$J$17*$G$33 -> 864 | J37: ='Ore Base Price Calculator'!$N$17*$G$33 -> 510.6 | K37: ='Ore Base Price Calculator'!$I$27*$G$33 -> 158.4 | L37: ='Ore Base Price Calculator'!$I$47*$G$33 -> 309.6 | M37: ='Ore Base Price Calculator'!$I$37*$G$33 -> 376.8 | O37: Gandew | P37: =P$7/('Salary Calculator'!$D$10/2) -> 109.8 | Q37: =Q$7/('Salary Calculator'!$D$10/2) -> 162 | R37: =R$7/('Salary Calculator'!$D$10/2) -> 95.7375 | S37: =S$7/('Salary Calculator'!$D$10/2) -> 29.7 | T37: =T$7/('Salary Calculator'!$D$10/2) -> 58.05 | U37: =U$7/('Salary Calculator'!$D$10/2) -> 70.65 | W37: Tier IV | X37: =P49 -> 73.2 | Y37: =Q49 -> 108 | Z37: =R49 -> 51.825 | AA37: =S49 -> 46.8 | AB37: =T49 -> 11.7 | AC37: =U49 -> 12.825
G38: Tolerideme | H38: ='Ore Base Price Calculator'!$I$18*$G$33 -> 657.6 | I38: ='Ore Base Price Calculator'!$J$18*$G$33 -> 936 | J38: ='Ore Base Price Calculator'!$N$18*$G$33 -> 486.6 | K38: ='Ore Base Price Calculator'!$I$28*$G$33 -> 446.4 | L38: ='Ore Base Price Calculator'!$I$48*$G$33 -> 165.6 | M38: ='Ore Base Price Calculator'!$I$38*$G$33 -> 208.8 | O38: Tolerideme | P38: =P$8/('Salary Calculator'!$D$10/2) -> 123.3 | Q38: =Q$8/('Salary Calculator'!$D$10/2) -> 175.5 | R38: =R$8/('Salary Calculator'!$D$10/2) -> 91.2375 | S38: =S$8/('Salary Calculator'!$D$10/2) -> 83.7 | T38: =T$8/('Salary Calculator'!$D$10/2) -> 31.05 | U38: =U$8/('Salary Calculator'!$D$10/2) -> 39.15
G39: Sanbi | H39: ='Ore Base Price Calculator'!$I$19*$G$33 -> 585.6 | I39: ='Ore Base Price Calculator'!$J$19*$G$33 -> 864 | J39: ='Ore Base Price Calculator'!$N$19*$G$33 -> 414.6 | K39: ='Ore Base Price Calculator'!$I$29*$G$33 -> 374.4 | L39: ='Ore Base Price Calculator'!$I$49*$G$33 -> 93.6 | M39: ='Ore Base Price Calculator'!$I$39*$G$33 -> 102.6 | O39: Sanbi | P39: =P$9/('Salary Calculator'!$D$10/2) -> 109.8 | Q39: =Q$9/('Salary Calculator'!$D$10/2) -> 162 | R39: =R$9/('Salary Calculator'!$D$10/2) -> 77.7375 | S39: =S$9/('Salary Calculator'!$D$10/2) -> 70.2 | T39: =T$9/('Salary Calculator'!$D$10/2) -> 17.55 | U39: =U$9/('Salary Calculator'!$D$10/2) -> 19.2375
O40: Tier III Avg Days | P40: =(((P39+P38+P37+P36)/4)) -> 113.175 | Q40: =(((Q39+Q38+Q37+Q36)/4)) -> 165.375 | R40: =(((R39+R38+R37+R36)/4)) -> 77.625 | S40: =(((S39+S38+S37+S36)/4)) -> 64.575 | T40: =(((T39+T38+T37+T36)/4)) -> 37.8 | U40: =(((U39+U38+U37+U36)/4)) -> 38.671875
O42: Full Set (Master level Work Days assuming 1/2 salary as savings)
P43: Iron | Q43: Steel | R43: Bone Wood | S43: Chitin | T43: Tibou | U43: Leather
P44: Tier IV | Q44: Tier IV | R44: Tier IV | S44: Tier IV | T44: Tier IV | U44: Tier IV
O45: UOM | P45: Days | Q45: Days | R45: Days | S45: Days | T45: Days | U45: Days
O46: Freeish | P46: =P$6/('Salary Calculator'!$E$10/2) -> 73.2 | Q46: =Q$6/('Salary Calculator'!$E$10/2) -> 108 | R46: =R$6/('Salary Calculator'!$E$10/2) -> 30.525 | S46: =S$6/('Salary Calculator'!$E$10/2) -> 49.8 | T46: =T$6/('Salary Calculator'!$E$10/2) -> 29.7 | U46: =U$6/('Salary Calculator'!$E$10/2) -> 17.1
O47: Gandew | P47: =P$7/('Salary Calculator'!$E$10/2) -> 73.2 | Q47: =Q$7/('Salary Calculator'!$E$10/2) -> 108 | R47: =R$7/('Salary Calculator'!$E$10/2) -> 63.825 | S47: =S$7/('Salary Calculator'!$E$10/2) -> 19.8 | T47: =T$7/('Salary Calculator'!$E$10/2) -> 38.7 | U47: =U$7/('Salary Calculator'!$E$10/2) -> 47.1
O48: Tolerideme | P48: =P$8/('Salary Calculator'!$E$10/2) -> 82.2 | Q48: =Q$8/('Salary Calculator'!$E$10/2) -> 117 | R48: =R$8/('Salary Calculator'!$E$10/2) -> 60.825 | S48: =S$8/('Salary Calculator'!$E$10/2) -> 55.8 | T48: =T$8/('Salary Calculator'!$E$10/2) -> 20.7 | U48: =U$8/('Salary Calculator'!$E$10/2) -> 26.1
O49: Sanbi | P49: =P$9/('Salary Calculator'!$E$10/2) -> 73.2 | Q49: =Q$9/('Salary Calculator'!$E$10/2) -> 108 | R49: =R$9/('Salary Calculator'!$E$10/2) -> 51.825 | S49: =S$9/('Salary Calculator'!$E$10/2) -> 46.8 | T49: =T$9/('Salary Calculator'!$E$10/2) -> 11.7 | U49: =U$9/('Salary Calculator'!$E$10/2) -> 12.825
O50: Tier IV Avg Days | P50: =(((P49+P48+P47+P46)/4)) -> 75.45 | Q50: =(((Q49+Q48+Q47+Q46)/4)) -> 110.25 | R50: =(((R49+R48+R47+R46)/4)) -> 51.75 | S50: =(((S49+S48+S47+S46)/4)) -> 43.05 | T50: =(((T49+T48+T47+T46)/4)) -> 25.2 | U50: =(((U49+U48+U47+U46)/4)) -> 25.78125

Sheet Weapon & Household Price Calcul
A1: Vars + Guide | G1: Weapons | M1: Soul Energy
A2: Region Color Guide | D2: Freeish Region (Tier III Avg) | G2: Daggers | M2: Sigil Rings
A3: Comparative Advantage | D3: Route | E3: Cost (Pearls) | G3: 3 | H3: Iron | I3: Steel | J3: Bone Wood | K3: Chitin | M3: 2 | N3: Soul Wood | O3: Black Wood
A4: From Freeish | D4: Gandew Region | E4: ='Distance Cost Calculator'!I16/'Distance Cost Calculator'!B14 -> 57 | G4: MATERIAL COST ALONE + SHIPPING. | M4: MATERIAL COST ALONE + SHIPPING.
A5: From Gandew | D5: Sanbi Region | E5: ='Distance Cost Calculator'!I17/'Distance Cost Calculator'!B14 -> 35 | G5: UOM | H5: Unit | I5: Unit | J5: Unit | K5: Unit | M5: UOM | N5: Unit | O5: Unit
A6: From Sanbi | D6: Tolerideme Region | E6: ='Distance Cost Calculator'!I18/'Distance Cost Calculator'!B14 -> 52 | G6: Freeish | H6: ='Ore Base Price Calculator'!$I$16*$G$3 -> 292.8 | I6: ='Ore Base Price Calculator'!$J$16*$G$3 -> 432 | J6: ='Ore Base Price Calculator'!$N$16*$G$3 -> 122.1 | K6: ='Ore Base Price Calculator'!$I$26*$G$3 -> 199.2 | M6: Freeish | N6: ='Ore Base Price Calculator'!$N$26*$M$3 -> 21.6 | O6: ='Ore Base Price Calculator'!$N$36*$M$3 -> 142.1
A7: From Tolerideme | D7: Gandew Region (Tier III Avg) | G7: Gandew | H7: ='Ore Base Price Calculator'!$I$17*$G$3 -> 292.8 | I7: ='Ore Base Price Calculator'!$J$17*$G$3 -> 432 | J7: ='Ore Base Price Calculator'!$N$17*$G$3 -> 255.3 | K7: ='Ore Base Price Calculator'!$I$27*$G$3 -> 79.2 | M7: Gandew | N7: ='Ore Base Price Calculator'!$N$27*$M$3 -> 101.6 | O7: ='Ore Base Price Calculator'!$N$37*$M$3 -> 62.1
A8: UOM Per 1kg | D8: Route | E8: Cost (Pearls) | G8: Tolerideme | H8: ='Ore Base Price Calculator'!$I$18*$G$3 -> 328.8 | I8: ='Ore Base Price Calculator'!$J$18*$G$3 -> 468 | J8: ='Ore Base Price Calculator'!$N$18*$G$3 -> 243.3 | K8: ='Ore Base Price Calculator'!$I$28*$G$3 -> 223.2 | M8: Tolerideme | N8: ='Ore Base Price Calculator'!$N$28*$M$3 -> 93.6 | O8: ='Ore Base Price Calculator'!$N$38*$M$3 -> 158.1
A9: Manual UOM | D9: Freeish Region | E9: ='Distance Cost Calculator'!Q16/'Distance Cost Calculator'!B14 -> 57 | G9: Sanbi | H9: ='Ore Base Price Calculator'!$I$19*$G$3 -> 292.8 | I9: ='Ore Base Price Calculator'!$J$19*$G$3 -> 432 | J9: ='Ore Base Price Calculator'!$N$19*$G$3 -> 207.3 | K9: ='Ore Base Price Calculator'!$I$29*$G$3 -> 187.2 | M9: Sanbi | N9: ='Ore Base Price Calculator'!$N$29*$M$3 -> 69.6 | O9: ='Ore Base Price Calculator'!$N$39*$M$3 -> 134.1
A10: Calculator Weight | D10: Sanbi Region | E10: ='Distance Cost Calculator'!Q17/'Distance Cost Calculator'!B14 -> 52
D11: Tolerideme Region | E11: ='Distance Cost Calculator'!Q18/'Distance Cost Calculator'!B14 -> 69
D12: Sanbi Region (Tier III Avg) | G12: Swords
D13: Route | E13: Cost (Pearls) | G13: 7 | H13: Iron | I13: Steel | J13: Bone Wood | K13: Chitin
D14: Freeish Region | E14: ='Distance Cost Calculator'!I21/'Distance Cost Calculator'!B14 -> 35 | G14: MATERIAL COST ALONE + SHIPPING.
D15: Gandew Region | E15: ='Distance Cost Calculator'!I22/'Distance Cost Calculator'!B14 -> 52 | G15: UOM | H15: Unit | I15: Unit | J15: Unit | K15: Unit
D16: Tolerideme Region | E16: ='Distance Cost Calculator'!I23/'Distance Cost Calculator'!B14 -> 18 | G16: Freeish | H16: ='Ore Base Price Calculator'!$I$16*$G$13 -> 683.2 | I16: ='Ore Base Price Calculator'!$J$16*$G$13 -> 1008 | J16: ='Ore Base Price Calculator'!$N$16*$G$13 -> 284.9 | K16: ='Ore Base Price Calculator'!$I$26*$G$13 -> 464.8
D17: Tolerideme Region (Tier III Avg) | G17: Gandew | H17: ='Ore Base Price Calculator'!$I$17*$G$13 -> 683.2 | I17: ='Ore Base Price Calculator'!$J$17*$G$13 -> 1008 | J17: ='Ore Base Price Calculator'!$N$17*$G$13 -> 595.7 | K17: ='Ore Base Price Calculator'!$I$27*$G$13 -> 184.8
D18: Route | E18: Cost (Pearls) | G18: Tolerideme | H18: ='Ore Base Price Calculator'!$I$18*$G$13 -> 767.2 | I18: ='Ore Base Price Calculator'!$J$18*$G$13 -> 1092 | J18: ='Ore Base Price Calculator'!$N$18*$G$13 -> 567.7 | K18: ='Ore Base Price Calculator'!$I$28*$G$13 -> 520.8
D19: Freeish Region | E19: ='Distance Cost Calculator'!Q21/'Distance Cost Calculator'!B14 -> 52 | G19: Sanbi | H19: ='Ore Base Price Calculator'!$I$19*$G$13 -> 683.2 | I19: ='Ore Base Price Calculator'!$J$19*$G$13 -> 1008 | J19: ='Ore Base Price Calculator'!$N$19*$G$13 -> 483.7 | K19: ='Ore Base Price Calculator'!$I$29*$G$13 -> 436.8
D20: Gandew Region | E20: ='Distance Cost Calculator'!Q22/'Distance Cost Calculator'!B14 -> 69
D21: Sanbi Region | E21: ='Distance Cost Calculator'!Q23/'Distance Cost Calculator'!B14 -> 18
G22: Longsword
G23: 15 | H23: Iron | I23: Steel | J23: Bone Wood | K23: Chitin
G24: MATERIAL COST ALONE + SHIPPING.
G25: UOM | H25: Unit | I25: Unit | J25: Unit | K25: Unit
G26: Freeish | H26: ='Ore Base Price Calculator'!$I$16*$G$23 -> 1464 | I26: ='Ore Base Price Calculator'!$J$16*$G$23 -> 2160 | J26: ='Ore Base Price Calculator'!$N$16*$G$23 -> 610.5 | K26: ='Ore Base Price Calculator'!$I$26*$G$23 -> 996
G27: Gandew | H27: ='Ore Base Price Calculator'!$I$17*$G$23 -> 1464 | I27: ='Ore Base Price Calculator'!$J$17*$G$23 -> 2160 | J27: ='Ore Base Price Calculator'!$N$17*$G$23 -> 1276.5 | K27: ='Ore Base Price Calculator'!$I$27*$G$23 -> 396
G28: Tolerideme | H28: ='Ore Base Price Calculator'!$I$18*$G$23 -> 1644 | I28: ='Ore Base Price Calculator'!$J$18*$G$23 -> 2340 | J28: ='Ore Base Price Calculator'!$N$18*$G$23 -> 1216.5 | K28: ='Ore Base Price Calculator'!$I$28*$G$23 -> 1116
G29: Sanbi | H29: ='Ore Base Price Calculator'!$I$19*$G$23 -> 1464 | I29: ='Ore Base Price Calculator'!$J$19*$G$23 -> 2160 | J29: ='Ore Base Price Calculator'!$N$19*$G$23 -> 1036.5 | K29: ='Ore Base Price Calculator'!$I$29*$G$23 -> 936
G32: Bow
G33: 6 | H33: Iron | I33: Steel | J33: Bone Wood | K33: Chitin
G34: MATERIAL COST ALONE + SHIPPING.
G35: UOM | H35: Unit | I35: Unit | J35: Unit | K35: Unit
G36: Freeish | H36: ='Ore Base Price Calculator'!$I$16*$G$33 -> 585.6 | I36: ='Ore Base Price Calculator'!$J$16*$G$33 -> 864 | J36: ='Ore Base Price Calculator'!$N$16*$G$33 -> 244.2 | K36: ='Ore Base Price Calculator'!$I$26*$G$33 -> 398.4
G37: Gandew | H37: ='Ore Base Price Calculator'!$I$17*$G$33 -> 585.6 | I37: ='Ore Base Price Calculator'!$J$17*$G$33 -> 864 | J37: ='Ore Base Price Calculator'!$N$17*$G$33 -> 510.6 | K37: ='Ore Base Price Calculator'!$I$27*$G$33 -> 158.4
G38: Tolerideme | H38: ='Ore Base Price Calculator'!$I$18*$G$33 -> 657.6 | I38: ='Ore Base Price Calculator'!$J$18*$G$33 -> 936 | J38: ='Ore Base Price Calculator'!$N$18*$G$33 -> 486.6 | K38: ='Ore Base Price Calculator'!$I$28*$G$33 -> 446.4
G39: Sanbi | H39: ='Ore Base Price Calculator'!$I$19*$G$33 -> 585.6 | I39: ='Ore Base Price Calculator'!$J$19*$G$33 -> 864 | J39: ='Ore Base Price Calculator'!$N$19*$G$33 -> 414.6 | K39: ='Ore Base Price Calculator'!$I$29*$G$33 -> 374.4
